{"arenasnow2": {"1": 347, "2": 688, "3": 489, "4": 329, "5": 213, "6": 142, "7": 131, "8": 96, "9": 98, "10": 78}, "arenasnow": {"1": 4018, "2": 1437, "3": 485, "4": 198, "5": 62, "6": 51, "7": 32, "8": 21, "9": 17, "10": 11}, "swimmingfrog": {"1": 110, "2": 191, "3": 189, "4": 180, "5": 151, "6": 153, "7": 132, "8": 127, "9": 96, "10": 98}, "_son_": {"1": 1, "2": 0, "3": 1, "4": 8, "5": 2, "6": 5, "7": 8, "8": 8, "9": 8, "10": 8}, "languidness": {"1": 0, "2": 5, "3": 4, "4": 12, "5": 11, "6": 9, "7": 14, "8": 17, "9": 15, "10": 14}, "s:fb:1341840049": {"1": 0, "2": 0, "3": 0, "4": 0, "5": 0, "6": 1, "7": 0, "8": 0, "9": 0, "10": 0}, "florentine": {"1": 212, "2": 320, "3": 258, "4": 203, "5": 168, "6": 134, "7": 95, "8": 92, "9": 78, "10": 59}, "goldjet30": {"1": 4, "2": 28, "3": 54, "4": 43, "5": 64, "6": 59, "7": 49, "8": 53, "9": 58, "10": 35}, "seabiscuit": {"1": 0, "2": 0, "3": 0, "4": 1, "5": 0, "6": 0, "7": 5, "8": 1, "9": 6, "10": 3}, "yzzahs": {"1": 1, "2": 2, "3": 16, "4": 14, "5": 12, "6": 27, "7": 28, "8": 40, "9": 21, "10": 38}, "kellysgreens": {"1": 43, "2": 4, "3": 3, "4": 0, "5": 3, "6": 2, "7": 3, "8": 1, "9": 0, "10": 1}, "fyda": {"1": 0, "2": 5, "3": 16, "4": 22, "5": 34, "6": 29, "7": 26, "8": 39, "9": 39, "10": 28}, "typingartist2": {"1": 2, "2": 14, "3": 37, "4": 52, "5": 68, "6": 64, "7": 95, "8": 104, "9": 104, "10": 95}, "mcaso123": {"1": 7, "2": 48, "3": 77, "4": 82, "5": 108, "6": 92, "7": 111, "8": 111, "9": 86, "10": 113}, "performancecheck": {"1": 93, "2": 124, "3": 100, "4": 84, "5": 55, "6": 44, "7": 47, "8": 25, "9": 27, "10": 23}, "kukkainn": {"1": 0, "2": 0, "3": 1, "4": 0, "5": 0, "6": 0, "7": 0, "8": 1, "9": 1, "10": 0}, "cmalmquist": {"1": 1, "2": 2, "3": 7, "4": 10, "5": 10, "6": 9, "7": 5, "8": 7, "9": 5, "10": 10}, "joshua728": {"1": 403, "2": 370, "3": 304, "4": 230, "5": 160, "6": 144, "7": 128, "8": 105, "9": 110, "10": 79}, "precariousgray": {"1": 0, "2": 2, "3": 2, "4": 8, "5": 7, "6": 7, "7": 6, "8": 8, "9": 10, "10": 9}, "chakk": {"1": 435, "2": 505, "3": 345, "4": 266, "5": 183, "6": 163, "7": 140, "8": 111, "9": 83, "10": 84}, "shazman": {"1": 54, "2": 123, "3": 171, "4": 198, "5": 213, "6": 207, "7": 161, "8": 167, "9": 178, "10": 159}, "hujala": {"1": 0, "2": 0, "3": 0, "4": 3, "5": 1, "6": 3, "7": 2, "8": 5, "9": 2, "10": 3}, "tsvukk": {"1": 4, "2": 12, "3": 25, "4": 21, "5": 23, "6": 26, "7": 34, "8": 23, "9": 29, "10": 28}, "slekap": {"1": 143, "2": 298, "3": 393, "4": 386, "5": 368, "6": 302, "7": 295, "8": 277, "9": 225, "10": 181}, "deroche1": {"1": 177, "2": 579, "3": 624, "4": 568, "5": 541, "6": 408, "7": 389, "8": 342, "9": 291, "10": 232}, "hurst": {"1": 2, "2": 3, "3": 7, "4": 15, "5": 17, "6": 17, "7": 15, "8": 27, "9": 24, "10": 19}, "han2000": {"1": 0, "2": 1, "3": 1, "4": 9, "5": 15, "6": 17, "7": 14, "8": 9, "9": 8, "10": 20}, "breakaaa": {"1": 0, "2": 0, "3": 0, "4": 0, "5": 0, "6": 0, "7": 1, "8": 3, "9": 0, "10": 1}, "mako640": {"1": 1, "2": 122, "3": 258, "4": 386, "5": 481, "6": 480, "7": 469, "8": 472, "9": 371, "10": 397}, "keegant": {"1": 89, "2": 155, "3": 227, "4": 222, "5": 268, "6": 239, "7": 276, "8": 241, "9": 250, "10": 235}, "alpha_panda": {"1": 31, "2": 155, "3": 225, "4": 215, "5": 258, "6": 242, "7": 217, "8": 182, "9": 193, "10": 186}, "nairadnal": {"1": 0, "2": 0, "3": 1, "4": 3, "5": 1, "6": 0, "7": 5, "8": 0, "9": 1, "10": 0}, "princesszelda": {"1": 0, "2": 0, "3": 0, "4": 0, "5": 1, "6": 0, "7": 0, "8": 0, "9": 0, "10": 0}, "eikomaniac": {"1": 7, "2": 29, "3": 39, "4": 61, "5": 64, "6": 70, "7": 81, "8": 92, "9": 80, "10": 86}, "mporsche02": {"1": 2, "2": 31, "3": 69, "4": 84, "5": 106, "6": 136, "7": 105, "8": 108, "9": 121, "10": 110}, "slowaccount": {"1": 233, "2": 383, "3": 411, "4": 356, "5": 277, "6": 277, "7": 250, "8": 199, "9": 215, "10": 206}, "tsvuk": {"1": 0, "2": 5, "3": 4, "4": 2, "5": 8, "6": 12, "7": 10, "8": 6, "9": 5, "10": 9}, "ap02": {"1": 27, "2": 65, "3": 70, "4": 70, "5": 52, "6": 53, "7": 40, "8": 37, "9": 41, "10": 37}, "itskevkev": {"1": 0, "2": 0, "3": 0, "4": 0, "5": 0, "6": 1, "7": 0, "8": 0, "9": 0, "10": 0}, "xayiver": {"1": 2, "2": 10, "3": 23, "4": 23, "5": 33, "6": 54, "7": 41, "8": 46, "9": 57, "10": 69}, "nonquitforizzy": {"1": 5, "2": 18, "3": 32, "4": 27, "5": 30, "6": 20, "7": 20, "8": 23, "9": 17, "10": 18}, "wlue": {"1": 0, "2": 0, "3": 1, "4": 3, "5": 1, "6": 0, "7": 3, "8": 4, "9": 1, "10": 3}, "atthetop": {"1": 79, "2": 183, "3": 300, "4": 378, "5": 405, "6": 422, "7": 390, "8": 391, "9": 339, "10": 296}, "pentalon": {"1": 1, "2": 38, "3": 76, "4": 111, "5": 131, "6": 148, "7": 159, "8": 140, "9": 131, "10": 121}, "sidd_": {"1": 0, "2": 10, "3": 23, "4": 28, "5": 36, "6": 44, "7": 70, "8": 69, "9": 80, "10": 98}, "arow": {"1": 0, "2": 0, "3": 0, "4": 0, "5": 1, "6": 0, "7": 0, "8": 1, "9": 2, "10": 0}, "afterbreakonly": {"1": 4, "2": 29, "3": 54, "4": 57, "5": 54, "6": 58, "7": 63, "8": 63, "9": 79, "10": 62}, "vuttar": {"1": 0, "2": 1, "3": 0, "4": 2, "5": 2, "6": 5, "7": 5, "8": 2, "9": 3, "10": 12}, "goldjet32": {"1": 198, "2": 157, "3": 144, "4": 100, "5": 85, "6": 48, "7": 33, "8": 19, "9": 18, "10": 10}, "chakkonmech": {"1": 9, "2": 12, "3": 15, "4": 19, "5": 15, "6": 11, "7": 13, "8": 4, "9": 9, "10": 6}, "oh_hai": {"1": 0, "2": 3, "3": 18, "4": 24, "5": 25, "6": 32, "7": 42, "8": 49, "9": 53, "10": 64}, "xeogran": {"1": 1, "2": 4, "3": 10, "4": 29, "5": 31, "6": 39, "7": 44, "8": 50, "9": 51, "10": 47}, "lalabird8": {"1": 12, "2": 22, "3": 40, "4": 34, "5": 25, "6": 26, "7": 39, "8": 36, "9": 30, "10": 27}, "escrow": {"1": 1, "2": 2, "3": 0, "4": 1, "5": 0, "6": 0, "7": 0, "8": 0, "9": 0, "10": 0}, "slowvinni": {"1": 1, "2": 2, "3": 12, "4": 19, "5": 17, "6": 30, "7": 48, "8": 45, "9": 55, "10": 62}, "rosewolf": {"1": 11, "2": 100, "3": 168, "4": 250, "5": 287, "6": 304, "7": 298, "8": 308, "9": 321, "10": 315}, "motsak": {"1": 0, "2": 0, "3": 1, "4": 0, "5": 0, "6": 0, "7": 0, "8": 0, "9": 0, "10": 0}, "supererik": {"1": 2, "2": 1, "3": 4, "4": 18, "5": 15, "6": 13, "7": 10, "8": 21, "9": 16, "10": 24}, "licahfox": {"1": 1, "2": 0, "3": 4, "4": 6, "5": 8, "6": 9, "7": 10, "8": 16, "9": 21, "10": 18}, "seanwrona": {"1": 3, "2": 3, "3": 3, "4": 3, "5": 0, "6": 0, "7": 0, "8": 1, "9": 1, "10": 0}, "minilek": {"1": 0, "2": 3, "3": 1, "4": 2, "5": 4, "6": 3, "7": 1, "8": 1, "9": 3, "10": 2}, "riverwalk3": {"1": 0, "2": 0, "3": 0, "4": 0, "5": 1, "6": 1, "7": 0, "8": 0, "9": 0, "10": 2}, "izanagiii": {"1": 0, "2": 14, "3": 15, "4": 30, "5": 31, "6": 27, "7": 36, "8": 32, "9": 46, "10": 45}, "landarian": {"1": 33, "2": 105, "3": 140, "4": 149, "5": 176, "6": 173, "7": 161, "8": 171, "9": 162, "10": 159}, "adamsky": {"1": 1, "2": 3, "3": 3, "4": 7, "5": 4, "6": 6, "7": 3, "8": 5, "9": 2, "10": 8}, "arc_sec": {"1": 44, "2": 224, "3": 326, "4": 388, "5": 392, "6": 382, "7": 320, "8": 307, "9": 253, "10": 216}, "fightin_phils": {"1": 0, "2": 1, "3": 7, "4": 11, "5": 20, "6": 26, "7": 23, "8": 43, "9": 44, "10": 51}, "foggyy": {"1": 84, "2": 148, "3": 176, "4": 239, "5": 230, "6": 212, "7": 214, "8": 215, "9": 201, "10": 215}, "clairez93": {"1": 0, "2": 0, "3": 0, "4": 0, "5": 1, "6": 0, "7": 1, "8": 1, "9": 1, "10": 0}, "jasheneverquitting": {"1": 0, "2": 0, "3": 0, "4": 0, "5": 0, "6": 1, "7": 0, "8": 0, "9": 0, "10": 0}, "zazaziing": {"1": 0, "2": 0, "3": 0, "4": 0, "5": 0, "6": 1, "7": 0, "8": 1, "9": 0, "10": 0}, "jashenonquitting": {"1": 0, "2": 0, "3": 3, "4": 8, "5": 11, "6": 13, "7": 15, "8": 21, "9": 37, "10": 28}, "awsomaw": {"1": 0, "2": 6, "3": 10, "4": 13, "5": 19, "6": 15, "7": 24, "8": 26, "9": 30, "10": 35}, "devilz91": {"1": 0, "2": 0, "3": 0, "4": 1, "5": 0, "6": 3, "7": 0, "8": 2, "9": 1, "10": 2}, "jessegarcia": {"1": 0, "2": 0, "3": 4, "4": 5, "5": 8, "6": 16, "7": 25, "8": 39, "9": 55, "10": 48}, "nitro2029": {"1": 0, "2": 0, "3": 1, "4": 3, "5": 3, "6": 1, "7": 5, "8": 3, "9": 5, "10": 8}, "johnbonham": {"1": 0, "2": 0, "3": 2, "4": 2, "5": 2, "6": 1, "7": 0, "8": 3, "9": 1, "10": 2}, "freshfastjashe": {"1": 3, "2": 4, "3": 9, "4": 15, "5": 23, "6": 22, "7": 23, "8": 30, "9": 31, "10": 36}, "momfoundthepoopsock": {"1": 0, "2": 0, "3": 1, "4": 2, "5": 3, "6": 4, "7": 4, "8": 7, "9": 5, "10": 2}, "treiderik": {"1": 0, "2": 3, "3": 17, "4": 16, "5": 23, "6": 28, "7": 24, "8": 40, "9": 34, "10": 32}, "scania730": {"1": 0, "2": 0, "3": 0, "4": 0, "5": 0, "6": 1, "7": 0, "8": 0, "9": 0, "10": 0}, "namawi": {"1": 0, "2": 0, "3": 0, "4": 1, "5": 0, "6": 0, "7": 2, "8": 0, "9": 0, "10": 0}, "continuum": {"1": 0, "2": 0, "3": 0, "4": 1, "5": 2, "6": 1, "7": 1, "8": 1, "9": 1, "10": 2}, "gowk": {"1": 0, "2": 0, "3": 1, "4": 2, "5": 5, "6": 5, "7": 3, "8": 8, "9": 1, "10": 5}, "maximumchris2": {"1": 2, "2": 1, "3": 3, "4": 8, "5": 3, "6": 7, "7": 10, "8": 6, "9": 14, "10": 11}, "actuallynonquitforlife": {"1": 0, "2": 11, "3": 21, "4": 16, "5": 24, "6": 23, "7": 34, "8": 38, "9": 28, "10": 33}, "despot": {"1": 0, "2": 4, "3": 13, "4": 38, "5": 56, "6": 72, "7": 80, "8": 73, "9": 96, "10": 106}, "firewolfrain": {"1": 2, "2": 9, "3": 14, "4": 12, "5": 20, "6": 34, "7": 27, "8": 31, "9": 32, "10": 40}, "hehehehee": {"1": 0, "2": 0, "3": 0, "4": 0, "5": 1, "6": 0, "7": 0, "8": 0, "9": 0, "10": 0}, "tenshinhan": {"1": 0, "2": 0, "3": 0, "4": 0, "5": 0, "6": 0, "7": 0, "8": 0, "9": 0, "10": 1}, "goddessjny": {"1": 0, "2": 0, "3": 0, "4": 1, "5": 0, "6": 0, "7": 0, "8": 0, "9": 0, "10": 0}, "valikor": {"1": 29, "2": 2, "3": 1, "4": 0, "5": 2, "6": 1, "7": 0, "8": 4, "9": 1, "10": 3}, "eric2choix37": {"1": 0, "2": 0, "3": 0, "4": 0, "5": 0, "6": 0, "7": 0, "8": 0, "9": 1, "10": 0}, "zigfried": {"1": 49, "2": 72, "3": 87, "4": 86, "5": 55, "6": 54, "7": 39, "8": 41, "9": 41, "10": 34}, "uberkelium": {"1": 0, "2": 4, "3": 7, "4": 11, "5": 14, "6": 18, "7": 21, "8": 24, "9": 28, "10": 35}, "sany5505": {"1": 6, "2": 11, "3": 15, "4": 23, "5": 22, "6": 35, "7": 36, "8": 44, "9": 43, "10": 43}, "maximumchris": {"1": 0, "2": 1, "3": 0, "4": 0, "5": 2, "6": 0, "7": 0, "8": 1, "9": 0, "10": 1}, "drunkkathy": {"1": 0, "2": 1, "3": 4, "4": 5, "5": 2, "6": 2, "7": 1, "8": 1, "9": 2, "10": 2}, "soupy": {"1": 1, "2": 1, "3": 6, "4": 6, "5": 7, "6": 9, "7": 13, "8": 11, "9": 11, "10": 10}, "volhosis": {"1": 9, "2": 25, "3": 60, "4": 62, "5": 83, "6": 93, "7": 115, "8": 87, "9": 114, "10": 113}, "hoetzen": {"1": 0, "2": 0, "3": 0, "4": 1, "5": 0, "6": 0, "7": 0, "8": 1, "9": 1, "10": 1}, "iamslow103": {"1": 2, "2": 5, "3": 11, "4": 23, "5": 29, "6": 24, "7": 27, "8": 37, "9": 42, "10": 35}, "s:fb:100001007693594": {"1": 0, "2": 0, "3": 0, "4": 1, "5": 0, "6": 0, "7": 0, "8": 0, "9": 0, "10": 1}, "7emp7a7ion": {"1": 5, "2": 22, "3": 20, "4": 32, "5": 39, "6": 25, "7": 33, "8": 40, "9": 26, "10": 41}, "s:fb:400731": {"1": 0, "2": 1, "3": 1, "4": 0, "5": 0, "6": 0, "7": 0, "8": 1, "9": 1, "10": 1}, "schollie": {"1": 0, "2": 1, "3": 3, "4": 5, "5": 10, "6": 17, "7": 14, "8": 26, "9": 27, "10": 28}, "nothisisjohn": {"1": 5, "2": 22, "3": 25, "4": 37, "5": 32, "6": 52, "7": 58, "8": 66, "9": 56, "10": 70}, "delawarelights": {"1": 1, "2": 6, "3": 7, "4": 13, "5": 13, "6": 17, "7": 23, "8": 24, "9": 32, "10": 25}, "mithadon": {"1": 0, "2": 0, "3": 1, "4": 3, "5": 3, "6": 4, "7": 3, "8": 4, "9": 6, "10": 12}, "mitch7656": {"1": 0, "2": 0, "3": 0, "4": 0, "5": 1, "6": 1, "7": 0, "8": 0, "9": 0, "10": 0}, "thefastmanthefast": {"1": 0, "2": 3, "3": 4, "4": 5, "5": 12, "6": 8, "7": 6, "8": 13, "9": 15, "10": 20}, "movin": {"1": 0, "2": 0, "3": 0, "4": 0, "5": 0, "6": 1, "7": 1, "8": 0, "9": 1, "10": 0}, "zachary989": {"1": 0, "2": 0, "3": 0, "4": 0, "5": 0, "6": 0, "7": 0, "8": 1, "9": 0, "10": 0}, "han1999": {"1": 0, "2": 0, "3": 0, "4": 0, "5": 1, "6": 2, "7": 3, "8": 1, "9": 1, "10": 1}, "melikepi": {"1": 0, "2": 0, "3": 1, "4": 4, "5": 2, "6": 1, "7": 8, "8": 5, "9": 8, "10": 3}, "alfee": {"1": 2, "2": 12, "3": 13, "4": 10, "5": 6, "6": 6, "7": 7, "8": 2, "9": 7, "10": 7}, "elrohir": {"1": 0, "2": 0, "3": 0, "4": 0, "5": 1, "6": 0, "7": 0, "8": 0, "9": 1, "10": 1}, "potatofishcake": {"1": 0, "2": 0, "3": 0, "4": 1, "5": 0, "6": 0, "7": 2, "8": 1, "9": 0, "10": 2}, "nonquit": {"1": 1, "2": 2, "3": 15, "4": 19, "5": 17, "6": 31, "7": 31, "8": 30, "9": 32, "10": 40}, "alister1986": {"1": 0, "2": 0, "3": 0, "4": 0, "5": 0, "6": 1, "7": 0, "8": 0, "9": 0, "10": 1}, "bruhhhhhh": {"1": 1, "2": 0, "3": 0, "4": 0, "5": 3, "6": 0, "7": 1, "8": 1, "9": 2, "10": 1}, "pentalow": {"1": 0, "2": 3, "3": 7, "4": 12, "5": 15, "6": 14, "7": 11, "8": 6, "9": 9, "10": 7}, "erikjscott": {"1": 0, "2": 0, "3": 0, "4": 1, "5": 0, "6": 4, "7": 3, "8": 4, "9": 4, "10": 1}, "michelleness": {"1": 0, "2": 0, "3": 0, "4": 0, "5": 1, "6": 0, "7": 0, "8": 2, "9": 3, "10": 0}, "richee": {"1": 1, "2": 3, "3": 3, "4": 6, "5": 7, "6": 11, "7": 10, "8": 10, "9": 3, "10": 10}, "oo0oo": {"1": 0, "2": 0, "3": 0, "4": 0, "5": 0, "6": 1, "7": 0, "8": 0, "9": 0, "10": 0}, "seanqueiroz": {"1": 0, "2": 0, "3": 0, "4": 0, "5": 0, "6": 0, "7": 1, "8": 0, "9": 0, "10": 0}, "l___l": {"1": 51, "2": 14, "3": 3, "4": 2, "5": 0, "6": 1, "7": 0, "8": 0, "9": 0, "10": 0}, "rogueart": {"1": 0, "2": 0, "3": 0, "4": 0, "5": 1, "6": 1, "7": 0, "8": 1, "9": 0, "10": 1}, "nathan546": {"1": 0, "2": 0, "3": 1, "4": 0, "5": 0, "6": 0, "7": 1, "8": 0, "9": 1, "10": 1}, "josh2005": {"1": 0, "2": 0, "3": 0, "4": 0, "5": 0, "6": 0, "7": 0, "8": 1, "9": 0, "10": 0}, "tedd": {"1": 0, "2": 0, "3": 0, "4": 0, "5": 0, "6": 0, "7": 0, "8": 0, "9": 1, "10": 0}, "zillkillyou": {"1": 0, "2": 0, "3": 0, "4": 0, "5": 1, "6": 0, "7": 0, "8": 0, "9": 0, "10": 0}, "kfzx": {"1": 0, "2": 1, "3": 1, "4": 2, "5": 1, "6": 6, "7": 2, "8": 1, "9": 2, "10": 0}, "mintynuggets": {"1": 0, "2": 1, "3": 0, "4": 0, "5": 0, "6": 0, "7": 0, "8": 0, "9": 0, "10": 0}, "chaktnqt": {"1": 6, "2": 2, "3": 5, "4": 2, "5": 2, "6": 2, "7": 1, "8": 0, "9": 1, "10": 1}, "ludovicianne": {"1": 0, "2": 0, "3": 0, "4": 1, "5": 1, "6": 0, "7": 1, "8": 0, "9": 1, "10": 1}, "01110000": {"1": 0, "2": 0, "3": 0, "4": 0, "5": 0, "6": 0, "7": 0, "8": 0, "9": 1, "10": 1}, "newbyx86": {"1": 0, "2": 0, "3": 0, "4": 2, "5": 0, "6": 2, "7": 0, "8": 0, "9": 0, "10": 0}, "keatonsmith": {"1": 0, "2": 0, "3": 1, "4": 0, "5": 0, "6": 0, "7": 3, "8": 0, "9": 3, "10": 2}, "cwhxoo": {"1": 0, "2": 0, "3": 0, "4": 0, "5": 0, "6": 1, "7": 0, "8": 0, "9": 0, "10": 0}, "amaranshin": {"1": 2, "2": 6, "3": 8, "4": 8, "5": 9, "6": 14, "7": 7, "8": 9, "9": 7, "10": 6}, "ibelieveingod2": {"1": 0, "2": 0, "3": 0, "4": 0, "5": 0, "6": 0, "7": 1, "8": 0, "9": 0, "10": 0}, "ianviv": {"1": 0, "2": 0, "3": 0, "4": 0, "5": 0, "6": 0, "7": 0, "8": 0, "9": 0, "10": 1}, "blaqshaq": {"1": 3, "2": 6, "3": 13, "4": 15, "5": 20, "6": 24, "7": 19, "8": 30, "9": 22, "10": 34}, "pobelt": {"1": 0, "2": 0, "3": 0, "4": 0, "5": 0, "6": 0, "7": 1, "8": 0, "9": 1, "10": 0}, "sonnhard": {"1": 0, "2": 0, "3": 0, "4": 1, "5": 0, "6": 0, "7": 1, "8": 0, "9": 0, "10": 0}, "brittanergh": {"1": 0, "2": 0, "3": 2, "4": 1, "5": 4, "6": 5, "7": 3, "8": 5, "9": 12, "10": 8}, "angeio": {"1": 0, "2": 0, "3": 3, "4": 5, "5": 13, "6": 5, "7": 11, "8": 11, "9": 11, "10": 11}, "dohak": {"1": 0, "2": 0, "3": 1, "4": 0, "5": 0, "6": 1, "7": 1, "8": 0, "9": 1, "10": 0}, "onehundredplus": {"1": 0, "2": 0, "3": 1, "4": 0, "5": 0, "6": 1, "7": 0, "8": 1, "9": 0, "10": 0}, "kathyacc": {"1": 0, "2": 2, "3": 4, "4": 6, "5": 6, "6": 7, "7": 10, "8": 4, "9": 3, "10": 11}, "dudepc": {"1": 0, "2": 0, "3": 0, "4": 0, "5": 1, "6": 0, "7": 0, "8": 0, "9": 0, "10": 0}, "hate_me_noob_haha": {"1": 0, "2": 0, "3": 0, "4": 0, "5": 0, "6": 1, "7": 0, "8": 0, "9": 0, "10": 0}, "teslaisfasterthanyou": {"1": 0, "2": 0, "3": 0, "4": 0, "5": 0, "6": 1, "7": 0, "8": 0, "9": 1, "10": 1}, "ayeyuhskuh": {"1": 0, "2": 0, "3": 4, "4": 1, "5": 2, "6": 4, "7": 4, "8": 10, "9": 18, "10": 13}, "sekk": {"1": 0, "2": 0, "3": 0, "4": 0, "5": 0, "6": 0, "7": 0, "8": 0, "9": 0, "10": 1}, "ckjy00": {"1": 0, "2": 0, "3": 0, "4": 0, "5": 0, "6": 0, "7": 0, "8": 0, "9": 1, "10": 0}, "allknowing": {"1": 0, "2": 0, "3": 1, "4": 0, "5": 0, "6": 0, "7": 0, "8": 1, "9": 1, "10": 0}, "hyper_racer": {"1": 0, "2": 0, "3": 8, "4": 8, "5": 16, "6": 14, "7": 17, "8": 11, "9": 19, "10": 24}, "bhopple": {"1": 0, "2": 0, "3": 0, "4": 3, "5": 1, "6": 1, "7": 0, "8": 0, "9": 0, "10": 0}, "delirious": {"1": 0, "2": 2, "3": 3, "4": 18, "5": 28, "6": 55, "7": 63, "8": 76, "9": 101, "10": 106}, "schizo_guy": {"1": 0, "2": 0, "3": 1, "4": 0, "5": 3, "6": 3, "7": 5, "8": 5, "9": 4, "10": 16}, "adam1205": {"1": 1, "2": 7, "3": 9, "4": 13, "5": 15, "6": 23, "7": 29, "8": 25, "9": 20, "10": 19}, "michyxo": {"1": 0, "2": 0, "3": 0, "4": 0, "5": 0, "6": 0, "7": 1, "8": 0, "9": 0, "10": 0}, "thegame53700": {"1": 1, "2": 0, "3": 0, "4": 0, "5": 0, "6": 0, "7": 0, "8": 1, "9": 0, "10": 2}, "spareribs": {"1": 0, "2": 1, "3": 1, "4": 3, "5": 1, "6": 1, "7": 4, "8": 4, "9": 6, "10": 8}, "maddogbv": {"1": 0, "2": 0, "3": 1, "4": 0, "5": 0, "6": 0, "7": 0, "8": 2, "9": 0, "10": 0}, "rosecryptodotcom": {"1": 0, "2": 0, "3": 0, "4": 0, "5": 1, "6": 1, "7": 1, "8": 2, "9": 1, "10": 2}, "thierry_rolland": {"1": 0, "2": 0, "3": 0, "4": 0, "5": 0, "6": 0, "7": 0, "8": 0, "9": 0, "10": 1}, "viellain": {"1": 1, "2": 2, "3": 2, "4": 3, "5": 8, "6": 6, "7": 15, "8": 23, "9": 29, "10": 31}, "aaronadams": {"1": 0, "2": 0, "3": 2, "4": 3, "5": 13, "6": 36, "7": 34, "8": 75, "9": 89, "10": 91}, "ultrasurf": {"1": 0, "2": 0, "3": 0, "4": 0, "5": 0, "6": 0, "7": 0, "8": 1, "9": 1, "10": 1}, "_houston_": {"1": 0, "2": 0, "3": 1, "4": 0, "5": 2, "6": 0, "7": 0, "8": 3, "9": 2, "10": 3}, "nosanewar": {"1": 0, "2": 0, "3": 0, "4": 0, "5": 0, "6": 0, "7": 0, "8": 0, "9": 1, "10": 0}, "ilysmn": {"1": 0, "2": 0, "3": 0, "4": 0, "5": 0, "6": 0, "7": 1, "8": 1, "9": 0, "10": 0}, "snoverpk": {"1": 0, "2": 0, "3": 0, "4": 1, "5": 0, "6": 2, "7": 7, "8": 6, "9": 14, "10": 16}, "x78978": {"1": 0, "2": 0, "3": 1, "4": 1, "5": 0, "6": 1, "7": 0, "8": 0, "9": 0, "10": 0}, "jweb_guru": {"1": 0, "2": 0, "3": 0, "4": 0, "5": 0, "6": 1, "7": 0, "8": 0, "9": 0, "10": 0}, "jujux": {"1": 0, "2": 0, "3": 0, "4": 0, "5": 1, "6": 0, "7": 1, "8": 0, "9": 0, "10": 1}, "deathpotato": {"1": 0, "2": 0, "3": 0, "4": 0, "5": 0, "6": 0, "7": 0, "8": 0, "9": 1, "10": 0}, "monkeyslp": {"1": 0, "2": 0, "3": 0, "4": 0, "5": 0, "6": 0, "7": 0, "8": 0, "9": 0, "10": 1}, "kukkains": {"1": 0, "2": 2, "3": 1, "4": 0, "5": 0, "6": 0, "7": 0, "8": 1, "9": 1, "10": 0}, "vonunov": {"1": 0, "2": 0, "3": 0, "4": 0, "5": 0, "6": 1, "7": 0, "8": 0, "9": 0, "10": 0}, "vinninq": {"1": 0, "2": 0, "3": 4, "4": 8, "5": 9, "6": 8, "7": 15, "8": 27, "9": 20, "10": 37}, "mokori": {"1": 0, "2": 0, "3": 0, "4": 0, "5": 0, "6": 0, "7": 0, "8": 0, "9": 1, "10": 0}, "satanist": {"1": 0, "2": 0, "3": 0, "4": 0, "5": 0, "6": 0, "7": 0, "8": 0, "9": 0, "10": 1}, "raikkonen": {"1": 0, "2": 0, "3": 0, "4": 0, "5": 0, "6": 0, "7": 1, "8": 0, "9": 0, "10": 1}, "lurkingbrah": {"1": 0, "2": 0, "3": 0, "4": 0, "5": 0, "6": 0, "7": 2, "8": 0, "9": 0, "10": 0}, "maweomg": {"1": 0, "2": 0, "3": 0, "4": 0, "5": 0, "6": 0, "7": 0, "8": 1, "9": 0, "10": 1}, "neonkarateguy": {"1": 0, "2": 0, "3": 0, "4": 0, "5": 0, "6": 0, "7": 0, "8": 0, "9": 1, "10": 0}, "mitchell_porsche": {"1": 1, "2": 1, "3": 2, "4": 1, "5": 1, "6": 1, "7": 1, "8": 4, "9": 3, "10": 2}, "modest_ked": {"1": 7, "2": 12, "3": 24, "4": 23, "5": 18, "6": 28, "7": 31, "8": 37, "9": 34, "10": 38}, "jooku": {"1": 0, "2": 0, "3": 0, "4": 0, "5": 0, "6": 0, "7": 0, "8": 0, "9": 1, "10": 0}, "bubchi89": {"1": 0, "2": 0, "3": 0, "4": 0, "5": 0, "6": 0, "7": 0, "8": 0, "9": 0, "10": 1}, "kukk": {"1": 0, "2": 0, "3": 0, "4": 0, "5": 0, "6": 0, "7": 0, "8": 0, "9": 0, "10": 2}, "lover_typeracer": {"1": 0, "2": 0, "3": 0, "4": 0, "5": 0, "6": 0, "7": 1, "8": 0, "9": 0, "10": 0}, "vinniwooh": {"1": 0, "2": 1, "3": 0, "4": 3, "5": 3, "6": 2, "7": 3, "8": 4, "9": 4, "10": 7}, "chickenquestion": {"1": 1, "2": 1, "3": 3, "4": 1, "5": 2, "6": 1, "7": 6, "8": 1, "9": 1, "10": 1}, "joshunq": {"1": 11, "2": 10, "3": 19, "4": 19, "5": 11, "6": 13, "7": 11, "8": 14, "9": 10, "10": 14}, "kevinski1": {"1": 0, "2": 0, "3": 1, "4": 1, "5": 0, "6": 0, "7": 2, "8": 0, "9": 0, "10": 0}, "novabond": {"1": 0, "2": 0, "3": 0, "4": 0, "5": 1, "6": 1, "7": 3, "8": 1, "9": 2, "10": 2}, "laggyfingers": {"1": 0, "2": 0, "3": 0, "4": 0, "5": 0, "6": 0, "7": 0, "8": 0, "9": 0, "10": 1}, "peace4u": {"1": 0, "2": 0, "3": 0, "4": 0, "5": 0, "6": 0, "7": 0, "8": 0, "9": 0, "10": 1}, "lil_plane": {"1": 2, "2": 0, "3": 3, "4": 2, "5": 3, "6": 0, "7": 1, "8": 0, "9": 1, "10": 0}, "lollercopter": {"1": 0, "2": 0, "3": 0, "4": 0, "5": 0, "6": 0, "7": 1, "8": 0, "9": 0, "10": 1}, "renarded": {"1": 0, "2": 0, "3": 0, "4": 0, "5": 0, "6": 1, "7": 0, "8": 0, "9": 1, "10": 1}, "s:fb:546562610": {"1": 0, "2": 0, "3": 0, "4": 0, "5": 0, "6": 0, "7": 0, "8": 0, "9": 1, "10": 0}, "dogpirate": {"1": 0, "2": 0, "3": 0, "4": 0, "5": 0, "6": 0, "7": 0, "8": 0, "9": 0, "10": 1}, "wilfordbrimley": {"1": 0, "2": 0, "3": 0, "4": 0, "5": 0, "6": 0, "7": 0, "8": 0, "9": 1, "10": 0}, "seventhsandwich": {"1": 0, "2": 0, "3": 0, "4": 0, "5": 0, "6": 0, "7": 0, "8": 1, "9": 0, "10": 0}, "s:fb:100001652630580": {"1": 0, "2": 0, "3": 0, "4": 0, "5": 0, "6": 0, "7": 0, "8": 1, "9": 0, "10": 1}, "qbz_": {"1": 0, "2": 0, "3": 0, "4": 0, "5": 0, "6": 0, "7": 1, "8": 0, "9": 0, "10": 0}, "learningdvorak": {"1": 0, "2": 0, "3": 0, "4": 0, "5": 0, "6": 0, "7": 0, "8": 0, "9": 1, "10": 0}, "musicismysoul": {"1": 0, "2": 0, "3": 0, "4": 0, "5": 0, "6": 1, "7": 1, "8": 0, "9": 0, "10": 1}, "fashizzle": {"1": 0, "2": 0, "3": 0, "4": 0, "5": 0, "6": 0, "7": 0, "8": 0, "9": 0, "10": 1}, "fartulence": {"1": 3, "2": 9, "3": 13, "4": 6, "5": 6, "6": 9, "7": 10, "8": 5, "9": 7, "10": 0}, "taran127": {"1": 0, "2": 2, "3": 3, "4": 7, "5": 9, "6": 9, "7": 12, "8": 8, "9": 7, "10": 8}, "k_u_k_k_a_i_n": {"1": 0, "2": 0, "3": 0, "4": 0, "5": 1, "6": 0, "7": 0, "8": 0, "9": 1, "10": 0}, "dustyng": {"1": 0, "2": 0, "3": 0, "4": 0, "5": 0, "6": 0, "7": 0, "8": 0, "9": 1, "10": 0}, "spazxtastiic": {"1": 0, "2": 0, "3": 0, "4": 0, "5": 0, "6": 0, "7": 0, "8": 1, "9": 0, "10": 0}, "younghomie": {"1": 0, "2": 0, "3": 0, "4": 0, "5": 0, "6": 0, "7": 0, "8": 1, "9": 0, "10": 0}, "jaylo": {"1": 0, "2": 0, "3": 0, "4": 0, "5": 0, "6": 0, "7": 3, "8": 0, "9": 2, "10": 2}, "zapakh": {"1": 0, "2": 0, "3": 0, "4": 0, "5": 0, "6": 0, "7": 0, "8": 1, "9": 0, "10": 0}, "flaneur": {"1": 0, "2": 1, "3": 2, "4": 7, "5": 3, "6": 8, "7": 4, "8": 14, "9": 11, "10": 13}, "reckful": {"1": 0, "2": 0, "3": 0, "4": 0, "5": 0, "6": 1, "7": 0, "8": 0, "9": 1, "10": 1}, "naturalcryptid": {"1": 1, "2": 1, "3": 0, "4": 2, "5": 2, "6": 2, "7": 4, "8": 0, "9": 0, "10": 1}, "mopquill": {"1": 0, "2": 0, "3": 0, "4": 0, "5": 0, "6": 0, "7": 0, "8": 1, "9": 0, "10": 0}, "linearithmetic": {"1": 0, "2": 0, "3": 0, "4": 0, "5": 0, "6": 0, "7": 0, "8": 0, "9": 0, "10": 2}, "rokilav": {"1": 0, "2": 0, "3": 0, "4": 0, "5": 0, "6": 0, "7": 0, "8": 0, "9": 1, "10": 0}, "iamfast8": {"1": 0, "2": 0, "3": 0, "4": 1, "5": 0, "6": 0, "7": 0, "8": 0, "9": 0, "10": 0}, "erniechiew": {"1": 0, "2": 0, "3": 1, "4": 1, "5": 0, "6": 1, "7": 2, "8": 1, "9": 5, "10": 4}, "matthewli": {"1": 0, "2": 0, "3": 0, "4": 0, "5": 0, "6": 0, "7": 1, "8": 0, "9": 0, "10": 0}, "hipppeng": {"1": 0, "2": 0, "3": 0, "4": 0, "5": 0, "6": 1, "7": 0, "8": 0, "9": 0, "10": 1}, "dont_cheat": {"1": 0, "2": 0, "3": 0, "4": 1, "5": 0, "6": 1, "7": 0, "8": 0, "9": 0, "10": 0}, "dryshade": {"1": 0, "2": 0, "3": 0, "4": 0, "5": 0, "6": 0, "7": 0, "8": 0, "9": 1, "10": 0}, "styrofoam": {"1": 0, "2": 0, "3": 1, "4": 1, "5": 2, "6": 8, "7": 10, "8": 27, "9": 25, "10": 29}, "rickzzy": {"1": 0, "2": 0, "3": 0, "4": 0, "5": 0, "6": 0, "7": 0, "8": 0, "9": 0, "10": 1}, "jashesupernonquit": {"1": 1, "2": 0, "3": 0, "4": 1, "5": 3, "6": 5, "7": 5, "8": 2, "9": 2, "10": 2}, "boop99": {"1": 0, "2": 0, "3": 0, "4": 0, "5": 0, "6": 2, "7": 0, "8": 0, "9": 0, "10": 1}, "pete_adriano_debiase": {"1": 5, "2": 1, "3": 1, "4": 0, "5": 1, "6": 0, "7": 1, "8": 1, "9": 0, "10": 0}, "1a2a": {"1": 0, "2": 0, "3": 0, "4": 1, "5": 1, "6": 0, "7": 1, "8": 0, "9": 4, "10": 0}, "kiwisandlimes": {"1": 0, "2": 0, "3": 0, "4": 0, "5": 0, "6": 0, "7": 0, "8": 1, "9": 0, "10": 0}, "yummykyounnys": {"1": 0, "2": 0, "3": 0, "4": 0, "5": 0, "6": 0, "7": 0, "8": 0, "9": 1, "10": 0}, "gewitterhexe": {"1": 0, "2": 0, "3": 0, "4": 1, "5": 0, "6": 0, "7": 0, "8": 1, "9": 1, "10": 1}, "fanta_practice": {"1": 0, "2": 0, "3": 0, "4": 0, "5": 0, "6": 0, "7": 0, "8": 0, "9": 0, "10": 1}, "crdm0": {"1": 0, "2": 0, "3": 0, "4": 1, "5": 1, "6": 4, "7": 1, "8": 3, "9": 5, "10": 8}, "itstiffie": {"1": 0, "2": 0, "3": 0, "4": 0, "5": 0, "6": 0, "7": 0, "8": 1, "9": 0, "10": 1}, "pentalonfan": {"1": 0, "2": 0, "3": 0, "4": 0, "5": 0, "6": 0, "7": 0, "8": 0, "9": 1, "10": 0}, "cloudat": {"1": 0, "2": 0, "3": 0, "4": 0, "5": 1, "6": 0, "7": 0, "8": 0, "9": 0, "10": 0}, "mostlynonquit": {"1": 1, "2": 7, "3": 22, "4": 37, "5": 43, "6": 48, "7": 39, "8": 53, "9": 49, "10": 36}, "laurelkwon": {"1": 0, "2": 0, "3": 0, "4": 0, "5": 0, "6": 0, "7": 0, "8": 1, "9": 0, "10": 0}, "cliffcatastrophe": {"1": 0, "2": 0, "3": 0, "4": 0, "5": 0, "6": 1, "7": 0, "8": 0, "9": 0, "10": 0}, "zyrrac2": {"1": 0, "2": 0, "3": 0, "4": 0, "5": 0, "6": 0, "7": 1, "8": 0, "9": 3, "10": 4}, "lizardman": {"1": 0, "2": 0, "3": 0, "4": 0, "5": 0, "6": 0, "7": 1, "8": 0, "9": 0, "10": 0}, "optiksniiper": {"1": 0, "2": 0, "3": 0, "4": 0, "5": 0, "6": 0, "7": 0, "8": 0, "9": 0, "10": 1}, "00zhero00": {"1": 0, "2": 0, "3": 0, "4": 0, "5": 0, "6": 2, "7": 0, "8": 1, "9": 0, "10": 0}, "emiglio": {"1": 0, "2": 1, "3": 4, "4": 1, "5": 2, "6": 8, "7": 5, "8": 9, "9": 4, "10": 5}, "ryanair": {"1": 0, "2": 0, "3": 0, "4": 0, "5": 0, "6": 0, "7": 0, "8": 0, "9": 1, "10": 0}, "vincemiller": {"1": 0, "2": 0, "3": 1, "4": 0, "5": 1, "6": 1, "7": 0, "8": 0, "9": 2, "10": 1}, "jnoquit": {"1": 0, "2": 0, "3": 0, "4": 0, "5": 0, "6": 1, "7": 0, "8": 1, "9": 1, "10": 1}, "smtchahal2": {"1": 0, "2": 0, "3": 0, "4": 0, "5": 0, "6": 1, "7": 0, "8": 0, "9": 0, "10": 0}, "wizard24h": {"1": 0, "2": 0, "3": 1, "4": 0, "5": 0, "6": 0, "7": 0, "8": 0, "9": 0, "10": 0}, "smarty_jones": {"1": 0, "2": 0, "3": 0, "4": 0, "5": 0, "6": 1, "7": 0, "8": 0, "9": 0, "10": 0}, "dooder": {"1": 0, "2": 0, "3": 0, "4": 0, "5": 0, "6": 1, "7": 0, "8": 0, "9": 0, "10": 0}, "noahbot": {"1": 0, "2": 0, "3": 0, "4": 0, "5": 0, "6": 0, "7": 0, "8": 0, "9": 0, "10": 1}, "birthdaykids": {"1": 1, "2": 0, "3": 0, "4": 0, "5": 0, "6": 0, "7": 0, "8": 0, "9": 0, "10": 1}, "skyhai": {"1": 0, "2": 0, "3": 0, "4": 0, "5": 0, "6": 0, "7": 0, "8": 0, "9": 0, "10": 1}, "qtnnqt": {"1": 0, "2": 0, "3": 0, "4": 0, "5": 0, "6": 1, "7": 0, "8": 0, "9": 0, "10": 1}, "ajmcserious": {"1": 0, "2": 0, "3": 0, "4": 0, "5": 0, "6": 0, "7": 0, "8": 0, "9": 1, "10": 1}, "john404": {"1": 0, "2": 0, "3": 1, "4": 0, "5": 0, "6": 0, "7": 0, "8": 0, "9": 0, "10": 0}, "max1017": {"1": 0, "2": 0, "3": 0, "4": 0, "5": 0, "6": 0, "7": 0, "8": 0, "9": 1, "10": 0}, "trashfish": {"1": 0, "2": 0, "3": 1, "4": 4, "5": 3, "6": 3, "7": 2, "8": 4, "9": 3, "10": 1}, "tanigon": {"1": 0, "2": 0, "3": 0, "4": 0, "5": 0, "6": 0, "7": 1, "8": 0, "9": 1, "10": 2}, "sandrini": {"1": 0, "2": 0, "3": 0, "4": 0, "5": 1, "6": 0, "7": 0, "8": 1, "9": 0, "10": 0}, "eikoman": {"1": 0, "2": 0, "3": 0, "4": 0, "5": 1, "6": 0, "7": 0, "8": 0, "9": 0, "10": 0}, "fastaccount": {"1": 2, "2": 2, "3": 3, "4": 3, "5": 4, "6": 5, "7": 9, "8": 8, "9": 9, "10": 7}, "plorksauce": {"1": 0, "2": 0, "3": 0, "4": 0, "5": 3, "6": 2, "7": 3, "8": 5, "9": 2, "10": 4}, "celinedreaming": {"1": 1, "2": 0, "3": 0, "4": 0, "5": 0, "6": 0, "7": 2, "8": 2, "9": 1, "10": 1}, "righttodie": {"1": 0, "2": 0, "3": 0, "4": 0, "5": 0, "6": 0, "7": 0, "8": 0, "9": 0, "10": 1}, "xylinx": {"1": 0, "2": 0, "3": 0, "4": 0, "5": 0, "6": 0, "7": 1, "8": 0, "9": 0, "10": 0}, "minilek2": {"1": 0, "2": 0, "3": 0, "4": 0, "5": 1, "6": 0, "7": 0, "8": 0, "9": 0, "10": 0}, "s:fb:568194117": {"1": 0, "2": 0, "3": 0, "4": 0, "5": 0, "6": 0, "7": 0, "8": 0, "9": 0, "10": 1}, "lalabird3": {"1": 0, "2": 0, "3": 1, "4": 1, "5": 0, "6": 1, "7": 1, "8": 1, "9": 1, "10": 0}, "rainnonquit": {"1": 0, "2": 4, "3": 4, "4": 9, "5": 5, "6": 23, "7": 28, "8": 27, "9": 34, "10": 44}, "weihceinre": {"1": 1, "2": 1, "3": 4, "4": 8, "5": 9, "6": 18, "7": 29, "8": 25, "9": 39, "10": 46}, "aime15": {"1": 0, "2": 0, "3": 1, "4": 0, "5": 0, "6": 0, "7": 0, "8": 0, "9": 0, "10": 0}, "andreaak00": {"1": 0, "2": 0, "3": 4, "4": 4, "5": 10, "6": 9, "7": 11, "8": 18, "9": 19, "10": 27}, "glevion": {"1": 0, "2": 0, "3": 0, "4": 3, "5": 1, "6": 2, "7": 0, "8": 4, "9": 3, "10": 3}, "myztikrice": {"1": 0, "2": 0, "3": 0, "4": 0, "5": 0, "6": 0, "7": 0, "8": 0, "9": 0, "10": 1}, "maxk1": {"1": 0, "2": 0, "3": 0, "4": 0, "5": 0, "6": 1, "7": 0, "8": 0, "9": 0, "10": 0}, "techcom0": {"1": 0, "2": 0, "3": 0, "4": 0, "5": 0, "6": 0, "7": 0, "8": 1, "9": 1, "10": 0}, "xhaopham": {"1": 0, "2": 0, "3": 0, "4": 0, "5": 0, "6": 0, "7": 1, "8": 0, "9": 0, "10": 0}, "csperler": {"1": 0, "2": 0, "3": 0, "4": 0, "5": 0, "6": 0, "7": 0, "8": 0, "9": 1, "10": 0}, "karedis": {"1": 0, "2": 0, "3": 0, "4": 0, "5": 0, "6": 0, "7": 0, "8": 0, "9": 1, "10": 0}, "sameer321": {"1": 0, "2": 0, "3": 0, "4": 0, "5": 0, "6": 0, "7": 0, "8": 0, "9": 1, "10": 0}, "every_text": {"1": 3, "2": 5, "3": 4, "4": 3, "5": 2, "6": 2, "7": 1, "8": 1, "9": 0, "10": 1}, "shadowyshadows": {"1": 0, "2": 0, "3": 0, "4": 0, "5": 0, "6": 1, "7": 1, "8": 1, "9": 2, "10": 2}, "deepspacen9ne": {"1": 0, "2": 0, "3": 0, "4": 0, "5": 0, "6": 0, "7": 1, "8": 0, "9": 0, "10": 0}, "clint_kun": {"1": 0, "2": 0, "3": 1, "4": 0, "5": 0, "6": 0, "7": 0, "8": 0, "9": 0, "10": 0}, "xrayy": {"1": 0, "2": 2, "3": 0, "4": 0, "5": 2, "6": 2, "7": 3, "8": 3, "9": 1, "10": 5}, "mj970325": {"1": 0, "2": 0, "3": 0, "4": 0, "5": 0, "6": 0, "7": 0, "8": 0, "9": 1, "10": 0}, "s:fb:1008909263": {"1": 0, "2": 0, "3": 0, "4": 0, "5": 0, "6": 0, "7": 0, "8": 0, "9": 1, "10": 1}, "onetruegodniccage": {"1": 0, "2": 0, "3": 0, "4": 0, "5": 1, "6": 0, "7": 0, "8": 0, "9": 2, "10": 1}, "gaddith": {"1": 0, "2": 0, "3": 0, "4": 0, "5": 0, "6": 0, "7": 0, "8": 0, "9": 1, "10": 0}, "micel1": {"1": 0, "2": 1, "3": 0, "4": 0, "5": 1, "6": 0, "7": 2, "8": 4, "9": 2, "10": 2}, "that_shoulder_guy": {"1": 0, "2": 1, "3": 1, "4": 1, "5": 3, "6": 2, "7": 2, "8": 1, "9": 3, "10": 2}, "drunkgnik": {"1": 0, "2": 0, "3": 0, "4": 0, "5": 0, "6": 0, "7": 1, "8": 0, "9": 0, "10": 0}, "lordduran": {"1": 0, "2": 0, "3": 0, "4": 0, "5": 0, "6": 1, "7": 0, "8": 0, "9": 0, "10": 0}, "flyingkeys": {"1": 0, "2": 1, "3": 4, "4": 0, "5": 2, "6": 2, "7": 5, "8": 2, "9": 1, "10": 2}, "rwong48": {"1": 0, "2": 0, "3": 0, "4": 0, "5": 0, "6": 0, "7": 0, "8": 0, "9": 0, "10": 1}, "nethis": {"1": 0, "2": 0, "3": 0, "4": 0, "5": 0, "6": 0, "7": 0, "8": 1, "9": 0, "10": 0}, "permil": {"1": 0, "2": 0, "3": 0, "4": 0, "5": 0, "6": 0, "7": 0, "8": 0, "9": 0, "10": 1}, "spintu": {"1": 0, "2": 0, "3": 0, "4": 0, "5": 0, "6": 0, "7": 1, "8": 0, "9": 0, "10": 0}, "desmonds": {"1": 0, "2": 0, "3": 0, "4": 0, "5": 0, "6": 0, "7": 1, "8": 0, "9": 0, "10": 0}, "ninjason": {"1": 0, "2": 0, "3": 0, "4": 0, "5": 0, "6": 0, "7": 1, "8": 0, "9": 0, "10": 0}, "chrisggwp": {"1": 0, "2": 0, "3": 0, "4": 0, "5": 0, "6": 0, "7": 1, "8": 1, "9": 1, "10": 2}, "umogbai": {"1": 0, "2": 0, "3": 0, "4": 0, "5": 0, "6": 0, "7": 0, "8": 1, "9": 0, "10": 0}, "preciousgravy": {"1": 0, "2": 1, "3": 1, "4": 2, "5": 1, "6": 0, "7": 1, "8": 2, "9": 2, "10": 7}, "e3e2": {"1": 0, "2": 0, "3": 0, "4": 0, "5": 3, "6": 4, "7": 3, "8": 5, "9": 3, "10": 2}, "jdrewbieber": {"1": 0, "2": 0, "3": 0, "4": 0, "5": 0, "6": 0, "7": 1, "8": 0, "9": 0, "10": 5}, "mononym_jisoo": {"1": 0, "2": 4, "3": 14, "4": 11, "5": 23, "6": 21, "7": 26, "8": 28, "9": 40, "10": 30}, "kr_24": {"1": 0, "2": 0, "3": 0, "4": 0, "5": 0, "6": 0, "7": 0, "8": 0, "9": 0, "10": 1}, "vinning": {"1": 0, "2": 0, "3": 0, "4": 2, "5": 2, "6": 2, "7": 5, "8": 6, "9": 18, "10": 11}, "elianaa1232": {"1": 0, "2": 0, "3": 0, "4": 0, "5": 0, "6": 0, "7": 0, "8": 0, "9": 1, "10": 0}, "michael910": {"1": 1, "2": 0, "3": 0, "4": 2, "5": 7, "6": 4, "7": 8, "8": 10, "9": 8, "10": 10}, "pseudobrittany": {"1": 0, "2": 0, "3": 0, "4": 0, "5": 0, "6": 0, "7": 0, "8": 0, "9": 1, "10": 1}, "newkeyboardlove": {"1": 0, "2": 0, "3": 1, "4": 1, "5": 1, "6": 2, "7": 0, "8": 6, "9": 3, "10": 3}, "uniquesnowflake": {"1": 0, "2": 0, "3": 0, "4": 2, "5": 1, "6": 8, "7": 10, "8": 2, "9": 12, "10": 14}, "uchihalol": {"1": 0, "2": 1, "3": 2, "4": 1, "5": 4, "6": 7, "7": 8, "8": 6, "9": 8, "10": 8}, "installed": {"1": 0, "2": 0, "3": 0, "4": 0, "5": 0, "6": 0, "7": 0, "8": 1, "9": 0, "10": 0}, "sigel": {"1": 0, "2": 0, "3": 0, "4": 0, "5": 0, "6": 0, "7": 0, "8": 4, "9": 3, "10": 2}, "2reckful": {"1": 0, "2": 0, "3": 0, "4": 0, "5": 0, "6": 0, "7": 0, "8": 1, "9": 0, "10": 1}, "realtyperbest": {"1": 0, "2": 0, "3": 0, "4": 0, "5": 0, "6": 0, "7": 1, "8": 0, "9": 0, "10": 0}, "kappalism": {"1": 0, "2": 0, "3": 0, "4": 0, "5": 0, "6": 1, "7": 1, "8": 1, "9": 2, "10": 3}, "tanoh": {"1": 0, "2": 1, "3": 1, "4": 1, "5": 1, "6": 3, "7": 2, "8": 4, "9": 2, "10": 3}, "pinkkea": {"1": 0, "2": 0, "3": 0, "4": 1, "5": 0, "6": 0, "7": 0, "8": 1, "9": 0, "10": 0}, "cometstech": {"1": 0, "2": 0, "3": 0, "4": 0, "5": 0, "6": 0, "7": 0, "8": 0, "9": 1, "10": 0}, "defined": {"1": 0, "2": 0, "3": 0, "4": 0, "5": 1, "6": 0, "7": 2, "8": 0, "9": 0, "10": 2}, "lucageorge": {"1": 0, "2": 0, "3": 0, "4": 0, "5": 0, "6": 1, "7": 1, "8": 3, "9": 4, "10": 5}, "charlieog": {"1": 0, "2": 0, "3": 0, "4": 6, "5": 22, "6": 40, "7": 44, "8": 40, "9": 41, "10": 44}, "jashehastoomanyroles": {"1": 0, "2": 0, "3": 1, "4": 0, "5": 0, "6": 1, "7": 0, "8": 1, "9": 0, "10": 1}, "alpha_hedgehog": {"1": 0, "2": 0, "3": 0, "4": 0, "5": 0, "6": 0, "7": 0, "8": 1, "9": 1, "10": 2}, "zyrrac4": {"1": 0, "2": 0, "3": 0, "4": 0, "5": 0, "6": 0, "7": 2, "8": 0, "9": 0, "10": 0}, "chawahir": {"1": 0, "2": 0, "3": 0, "4": 0, "5": 0, "6": 0, "7": 0, "8": 0, "9": 1, "10": 0}, "codecub": {"1": 3, "2": 0, "3": 0, "4": 0, "5": 0, "6": 2, "7": 1, "8": 0, "9": 1, "10": 2}, "thoomb": {"1": 0, "2": 2, "3": 1, "4": 1, "5": 5, "6": 2, "7": 3, "8": 3, "9": 6, "10": 11}, "m4dara": {"1": 1, "2": 3, "3": 4, "4": 2, "5": 3, "6": 5, "7": 3, "8": 1, "9": 3, "10": 0}, "humanwaste": {"1": 1, "2": 1, "3": 4, "4": 7, "5": 17, "6": 17, "7": 13, "8": 9, "9": 26, "10": 24}, "derumisis": {"1": 0, "2": 0, "3": 0, "4": 0, "5": 0, "6": 0, "7": 0, "8": 0, "9": 1, "10": 0}, "guest": {"1": 0, "2": 1, "3": 1, "4": 0, "5": 1, "6": 0, "7": 0, "8": 0, "9": 0, "10": 0}, "nmyo": {"1": 0, "2": 0, "3": 0, "4": 1, "5": 0, "6": 0, "7": 0, "8": 2, "9": 0, "10": 0}, "andreaak": {"1": 0, "2": 0, "3": 1, "4": 0, "5": 0, "6": 0, "7": 1, "8": 2, "9": 3, "10": 2}, "disclo5ure": {"1": 0, "2": 0, "3": 0, "4": 0, "5": 4, "6": 5, "7": 2, "8": 6, "9": 6, "10": 11}, "hypasuper": {"1": 0, "2": 0, "3": 1, "4": 0, "5": 1, "6": 1, "7": 1, "8": 3, "9": 4, "10": 1}, "guestban2": {"1": 0, "2": 1, "3": 0, "4": 0, "5": 0, "6": 0, "7": 0, "8": 1, "9": 0, "10": 0}, "gnikgg": {"1": 0, "2": 1, "3": 0, "4": 0, "5": 0, "6": 1, "7": 3, "8": 5, "9": 5, "10": 3}, "jetter06": {"1": 0, "2": 0, "3": 0, "4": 0, "5": 0, "6": 0, "7": 0, "8": 1, "9": 0, "10": 0}, "tkpwaeub": {"1": 1, "2": 0, "3": 0, "4": 0, "5": 0, "6": 0, "7": 0, "8": 2, "9": 2, "10": 3}, "johnnew": {"1": 0, "2": 0, "3": 0, "4": 0, "5": 0, "6": 1, "7": 2, "8": 0, "9": 4, "10": 5}, "andreaclare": {"1": 0, "2": 0, "3": 1, "4": 0, "5": 0, "6": 0, "7": 0, "8": 0, "9": 0, "10": 0}, "thefatninja69": {"1": 0, "2": 0, "3": 0, "4": 2, "5": 0, "6": 2, "7": 1, "8": 2, "9": 4, "10": 0}, "daniel598": {"1": 0, "2": 0, "3": 0, "4": 1, "5": 1, "6": 1, "7": 6, "8": 4, "9": 5, "10": 6}, "accurayc": {"1": 0, "2": 0, "3": 0, "4": 0, "5": 0, "6": 0, "7": 0, "8": 0, "9": 1, "10": 3}, "jych": {"1": 0, "2": 0, "3": 0, "4": 0, "5": 0, "6": 0, "7": 0, "8": 0, "9": 0, "10": 1}, "gumdroptype": {"1": 0, "2": 0, "3": 0, "4": 0, "5": 1, "6": 0, "7": 0, "8": 0, "9": 1, "10": 0}, "swaax": {"1": 0, "2": 0, "3": 0, "4": 0, "5": 0, "6": 0, "7": 0, "8": 0, "9": 1, "10": 4}, "drakkus": {"1": 0, "2": 0, "3": 0, "4": 0, "5": 0, "6": 0, "7": 0, "8": 1, "9": 1, "10": 0}, "infectmecoviddaddy": {"1": 0, "2": 0, "3": 1, "4": 1, "5": 3, "6": 2, "7": 0, "8": 1, "9": 0, "10": 1}, "usaintraining": {"1": 0, "2": 1, "3": 0, "4": 1, "5": 1, "6": 3, "7": 5, "8": 1, "9": 8, "10": 5}, "7031": {"1": 0, "2": 0, "3": 0, "4": 0, "5": 0, "6": 0, "7": 0, "8": 0, "9": 0, "10": 1}, "eagleloftrules": {"1": 0, "2": 0, "3": 2, "4": 1, "5": 0, "6": 4, "7": 5, "8": 3, "9": 7, "10": 5}, "primalknight": {"1": 0, "2": 1, "3": 0, "4": 0, "5": 1, "6": 0, "7": 3, "8": 0, "9": 5, "10": 3}, "jyin": {"1": 0, "2": 0, "3": 0, "4": 0, "5": 0, "6": 6, "7": 3, "8": 5, "9": 12, "10": 11}, "apackofsmarties": {"1": 0, "2": 4, "3": 0, "4": 0, "5": 2, "6": 3, "7": 2, "8": 3, "9": 2, "10": 1}, "fouracle": {"1": 1, "2": 0, "3": 0, "4": 1, "5": 0, "6": 5, "7": 5, "8": 0, "9": 7, "10": 6}, "dragoncityjose": {"1": 1, "2": 0, "3": 2, "4": 3, "5": 3, "6": 2, "7": 4, "8": 4, "9": 7, "10": 6}, "siglemic": {"1": 0, "2": 1, "3": 0, "4": 3, "5": 5, "6": 1, "7": 9, "8": 8, "9": 6, "10": 5}, "emporia": {"1": 0, "2": 0, "3": 3, "4": 0, "5": 2, "6": 4, "7": 6, "8": 3, "9": 2, "10": 6}, "skulkzyy": {"1": 0, "2": 0, "3": 0, "4": 1, "5": 0, "6": 0, "7": 0, "8": 0, "9": 0, "10": 1}, "goat_56": {"1": 1, "2": 0, "3": 0, "4": 0, "5": 0, "6": 0, "7": 0, "8": 0, "9": 0, "10": 0}, "actuallyactuallynonquitforlife": {"1": 0, "2": 0, "3": 0, "4": 0, "5": 0, "6": 3, "7": 0, "8": 1, "9": 1, "10": 1}, "o________o": {"1": 0, "2": 1, "3": 1, "4": 3, "5": 5, "6": 2, "7": 14, "8": 7, "9": 11, "10": 9}, "alianel": {"1": 0, "2": 0, "3": 0, "4": 0, "5": 1, "6": 0, "7": 0, "8": 0, "9": 0, "10": 0}, "dowon": {"1": 0, "2": 0, "3": 0, "4": 0, "5": 1, "6": 0, "7": 2, "8": 2, "9": 0, "10": 3}, "b___u_________d__d_______y": {"1": 0, "2": 0, "3": 0, "4": 0, "5": 0, "6": 1, "7": 1, "8": 0, "9": 2, "10": 3}, "adenx": {"1": 0, "2": 0, "3": 0, "4": 0, "5": 0, "6": 0, "7": 0, "8": 1, "9": 0, "10": 0}, "kathygivingday": {"1": 0, "2": 0, "3": 1, "4": 0, "5": 0, "6": 0, "7": 1, "8": 0, "9": 0, "10": 0}, "kastrit": {"1": 0, "2": 0, "3": 0, "4": 0, "5": 0, "6": 0, "7": 0, "8": 1, "9": 0, "10": 0}, "kareemhunt": {"1": 0, "2": 0, "3": 1, "4": 0, "5": 1, "6": 0, "7": 0, "8": 0, "9": 0, "10": 4}, "initializesahib": {"1": 0, "2": 0, "3": 0, "4": 0, "5": 0, "6": 0, "7": 0, "8": 0, "9": 1, "10": 0}, "jchwa": {"1": 0, "2": 0, "3": 0, "4": 0, "5": 0, "6": 0, "7": 0, "8": 0, "9": 0, "10": 1}, "vinnychase": {"1": 0, "2": 0, "3": 1, "4": 0, "5": 0, "6": 0, "7": 0, "8": 0, "9": 0, "10": 0}, "lollipop_lover": {"1": 0, "2": 1, "3": 2, "4": 2, "5": 2, "6": 0, "7": 3, "8": 4, "9": 0, "10": 3}, "residober": {"1": 0, "2": 1, "3": 1, "4": 1, "5": 5, "6": 1, "7": 2, "8": 5, "9": 7, "10": 8}, "stabsterx1x": {"1": 0, "2": 0, "3": 0, "4": 0, "5": 1, "6": 0, "7": 0, "8": 0, "9": 0, "10": 0}, "fricative": {"1": 1, "2": 0, "3": 1, "4": 0, "5": 0, "6": 0, "7": 0, "8": 0, "9": 1, "10": 0}, "mikeyirl": {"1": 0, "2": 0, "3": 0, "4": 0, "5": 0, "6": 0, "7": 0, "8": 1, "9": 0, "10": 1}, "kingstealth": {"1": 0, "2": 0, "3": 1, "4": 0, "5": 0, "6": 2, "7": 5, "8": 0, "9": 3, "10": 2}, "rumpeltutzen": {"1": 0, "2": 0, "3": 0, "4": 0, "5": 0, "6": 0, "7": 0, "8": 0, "9": 1, "10": 2}, "theboi4": {"1": 0, "2": 0, "3": 0, "4": 0, "5": 0, "6": 1, "7": 1, "8": 0, "9": 0, "10": 1}, "someguysnonquit": {"1": 0, "2": 0, "3": 0, "4": 0, "5": 0, "6": 0, "7": 1, "8": 0, "9": 0, "10": 2}, "igumdropx": {"1": 0, "2": 0, "3": 0, "4": 1, "5": 1, "6": 0, "7": 1, "8": 2, "9": 1, "10": 0}, "bblaise": {"1": 0, "2": 0, "3": 0, "4": 0, "5": 0, "6": 1, "7": 2, "8": 1, "9": 9, "10": 4}, "vdud3": {"1": 0, "2": 0, "3": 0, "4": 0, "5": 0, "6": 0, "7": 0, "8": 2, "9": 1, "10": 1}, "jlachney": {"1": 0, "2": 0, "3": 0, "4": 0, "5": 1, "6": 1, "7": 8, "8": 4, "9": 7, "10": 7}, "traben": {"1": 0, "2": 0, "3": 0, "4": 0, "5": 0, "6": 1, "7": 0, "8": 1, "9": 1, "10": 1}, "gnik": {"1": 0, "2": 0, "3": 0, "4": 0, "5": 0, "6": 1, "7": 0, "8": 0, "9": 0, "10": 0}, "s3rez": {"1": 0, "2": 1, "3": 0, "4": 0, "5": 1, "6": 0, "7": 1, "8": 0, "9": 0, "10": 0}, "_v3_": {"1": 0, "2": 0, "3": 0, "4": 0, "5": 0, "6": 1, "7": 0, "8": 1, "9": 1, "10": 3}, "nonquithenryzhou": {"1": 0, "2": 0, "3": 0, "4": 1, "5": 0, "6": 0, "7": 1, "8": 4, "9": 0, "10": 0}, "c0decub": {"1": 0, "2": 0, "3": 0, "4": 0, "5": 1, "6": 2, "7": 0, "8": 1, "9": 0, "10": 2}, "iwantmedals": {"1": 0, "2": 0, "3": 0, "4": 0, "5": 2, "6": 0, "7": 1, "8": 0, "9": 2, "10": 1}, "lhykv": {"1": 0, "2": 0, "3": 0, "4": 1, "5": 1, "6": 4, "7": 6, "8": 7, "9": 11, "10": 9}, "p0sh": {"1": 0, "2": 0, "3": 0, "4": 0, "5": 1, "6": 0, "7": 1, "8": 0, "9": 1, "10": 3}, "thedude123": {"1": 0, "2": 0, "3": 0, "4": 1, "5": 1, "6": 2, "7": 2, "8": 1, "9": 2, "10": 2}, "actuallymostlynonquit": {"1": 1, "2": 0, "3": 0, "4": 1, "5": 2, "6": 1, "7": 3, "8": 5, "9": 1, "10": 3}, "elusoryx": {"1": 0, "2": 0, "3": 0, "4": 0, "5": 1, "6": 0, "7": 0, "8": 0, "9": 0, "10": 1}, "hospitalforsouls2": {"1": 2, "2": 1, "3": 1, "4": 4, "5": 9, "6": 7, "7": 16, "8": 14, "9": 18, "10": 24}, "yada": {"1": 0, "2": 0, "3": 0, "4": 0, "5": 0, "6": 0, "7": 1, "8": 0, "9": 0, "10": 0}, "theonlyjan": {"1": 0, "2": 0, "3": 0, "4": 0, "5": 0, "6": 1, "7": 0, "8": 0, "9": 0, "10": 0}, "frazwah": {"1": 0, "2": 0, "3": 1, "4": 0, "5": 0, "6": 0, "7": 0, "8": 0, "9": 0, "10": 0}, "itay5621": {"1": 0, "2": 0, "3": 0, "4": 0, "5": 0, "6": 1, "7": 1, "8": 0, "9": 1, "10": 1}, "bennasaur": {"1": 0, "2": 0, "3": 0, "4": 0, "5": 0, "6": 0, "7": 0, "8": 0, "9": 0, "10": 1}, "notquitting": {"1": 0, "2": 0, "3": 0, "4": 0, "5": 0, "6": 0, "7": 0, "8": 0, "9": 0, "10": 2}, "hreyfill": {"1": 0, "2": 0, "3": 0, "4": 0, "5": 0, "6": 0, "7": 2, "8": 1, "9": 2, "10": 4}, "dondeestanlasdrugs": {"1": 0, "2": 0, "3": 2, "4": 0, "5": 1, "6": 0, "7": 0, "8": 0, "9": 0, "10": 0}, "nonquitforbooly": {"1": 0, "2": 0, "3": 0, "4": 0, "5": 0, "6": 0, "7": 0, "8": 0, "9": 1, "10": 0}, "scaphism00": {"1": 0, "2": 0, "3": 0, "4": 0, "5": 0, "6": 0, "7": 0, "8": 0, "9": 1, "10": 2}, "qwerty91994": {"1": 0, "2": 0, "3": 0, "4": 0, "5": 1, "6": 2, "7": 0, "8": 0, "9": 1, "10": 1}, "slekaq": {"1": 0, "2": 0, "3": 0, "4": 0, "5": 0, "6": 0, "7": 0, "8": 0, "9": 0, "10": 2}, "juij": {"1": 0, "2": 0, "3": 0, "4": 0, "5": 0, "6": 1, "7": 0, "8": 0, "9": 0, "10": 0}, "haagentii": {"1": 0, "2": 0, "3": 0, "4": 0, "5": 1, "6": 0, "7": 0, "8": 0, "9": 3, "10": 0}, "hoejebent": {"1": 0, "2": 0, "3": 0, "4": 0, "5": 0, "6": 1, "7": 0, "8": 1, "9": 0, "10": 1}, "serqph": {"1": 0, "2": 0, "3": 0, "4": 0, "5": 0, "6": 0, "7": 1, "8": 1, "9": 0, "10": 1}, "wilburt": {"1": 0, "2": 0, "3": 1, "4": 2, "5": 2, "6": 3, "7": 6, "8": 1, "9": 2, "10": 7}, "pain": {"1": 0, "2": 0, "3": 0, "4": 0, "5": 0, "6": 0, "7": 0, "8": 1, "9": 0, "10": 0}, "kenixx": {"1": 0, "2": 0, "3": 0, "4": 0, "5": 0, "6": 0, "7": 0, "8": 1, "9": 0, "10": 1}, "mispelled": {"1": 1, "2": 0, "3": 0, "4": 0, "5": 1, "6": 0, "7": 1, "8": 1, "9": 0, "10": 0}, "azathoth1": {"1": 0, "2": 1, "3": 0, "4": 0, "5": 1, "6": 1, "7": 0, "8": 1, "9": 3, "10": 1}, "chickentyper": {"1": 0, "2": 0, "3": 0, "4": 0, "5": 0, "6": 0, "7": 1, "8": 0, "9": 1, "10": 0}, "elitype": {"1": 0, "2": 0, "3": 0, "4": 0, "5": 0, "6": 0, "7": 1, "8": 1, "9": 0, "10": 1}, "lord_of_the_simps": {"1": 0, "2": 0, "3": 0, "4": 0, "5": 0, "6": 1, "7": 0, "8": 0, "9": 0, "10": 0}, "dawsonas_": {"1": 0, "2": 0, "3": 0, "4": 0, "5": 0, "6": 0, "7": 1, "8": 0, "9": 0, "10": 0}, "slatebreaker": {"1": 0, "2": 1, "3": 1, "4": 0, "5": 0, "6": 1, "7": 0, "8": 2, "9": 1, "10": 0}, "vathlauss": {"1": 0, "2": 0, "3": 0, "4": 0, "5": 0, "6": 1, "7": 0, "8": 0, "9": 0, "10": 0}, "humancyclone": {"1": 0, "2": 0, "3": 0, "4": 0, "5": 0, "6": 0, "7": 0, "8": 0, "9": 1, "10": 0}, "toadys": {"1": 0, "2": 0, "3": 0, "4": 0, "5": 0, "6": 1, "7": 0, "8": 0, "9": 0, "10": 0}, "ghoulszz": {"1": 0, "2": 0, "3": 0, "4": 0, "5": 0, "6": 0, "7": 0, "8": 0, "9": 1, "10": 1}, "excessivefreudianslip": {"1": 0, "2": 0, "3": 0, "4": 1, "5": 3, "6": 0, "7": 4, "8": 2, "9": 1, "10": 2}, "whatalife": {"1": 0, "2": 0, "3": 0, "4": 1, "5": 1, "6": 0, "7": 1, "8": 0, "9": 1, "10": 1}, "notcheatingbtwdesktop": {"1": 0, "2": 0, "3": 0, "4": 0, "5": 0, "6": 0, "7": 1, "8": 0, "9": 0, "10": 5}, "laptop_op": {"1": 0, "2": 0, "3": 0, "4": 0, "5": 0, "6": 1, "7": 1, "8": 0, "9": 0, "10": 1}, "slowbutaccurate": {"1": 0, "2": 0, "3": 0, "4": 0, "5": 0, "6": 0, "7": 0, "8": 1, "9": 0, "10": 1}, "scaphism": {"1": 0, "2": 0, "3": 0, "4": 0, "5": 0, "6": 1, "7": 0, "8": 0, "9": 3, "10": 5}, "250wpmtarget": {"1": 0, "2": 0, "3": 0, "4": 0, "5": 0, "6": 0, "7": 1, "8": 0, "9": 0, "10": 1}, "williamjwu4": {"1": 0, "2": 0, "3": 0, "4": 1, "5": 0, "6": 0, "7": 0, "8": 0, "9": 0, "10": 1}, "vielleasd": {"1": 0, "2": 1, "3": 0, "4": 0, "5": 1, "6": 2, "7": 0, "8": 1, "9": 0, "10": 0}, "synx": {"1": 0, "2": 0, "3": 0, "4": 0, "5": 0, "6": 0, "7": 0, "8": 0, "9": 1, "10": 0}, "waltertmd": {"1": 0, "2": 0, "3": 0, "4": 0, "5": 1, "6": 0, "7": 0, "8": 1, "9": 0, "10": 1}, "macieje": {"1": 0, "2": 0, "3": 0, "4": 0, "5": 0, "6": 1, "7": 1, "8": 0, "9": 1, "10": 3}, "wiggir": {"1": 0, "2": 0, "3": 0, "4": 0, "5": 0, "6": 0, "7": 1, "8": 0, "9": 0, "10": 0}, "adma": {"1": 0, "2": 0, "3": 0, "4": 0, "5": 0, "6": 0, "7": 2, "8": 0, "9": 0, "10": 1}, "octalon": {"1": 0, "2": 0, "3": 0, "4": 0, "5": 0, "6": 0, "7": 0, "8": 1, "9": 0, "10": 1}, "thecbrady": {"1": 0, "2": 0, "3": 0, "4": 0, "5": 0, "6": 0, "7": 1, "8": 0, "9": 0, "10": 0}, "andrewhan": {"1": 0, "2": 0, "3": 0, "4": 1, "5": 0, "6": 0, "7": 0, "8": 1, "9": 0, "10": 1}, "etay5621": {"1": 0, "2": 0, "3": 0, "4": 0, "5": 0, "6": 0, "7": 1, "8": 1, "9": 0, "10": 0}, "lsp425": {"1": 0, "2": 0, "3": 0, "4": 0, "5": 0, "6": 0, "7": 0, "8": 1, "9": 0, "10": 0}, "eli_ayase": {"1": 0, "2": 1, "3": 0, "4": 0, "5": 0, "6": 2, "7": 3, "8": 0, "9": 1, "10": 1}, "veryjos": {"1": 0, "2": 0, "3": 0, "4": 0, "5": 0, "6": 0, "7": 1, "8": 0, "9": 1, "10": 0}, "zeox": {"1": 0, "2": 0, "3": 0, "4": 0, "5": 0, "6": 0, "7": 0, "8": 0, "9": 1, "10": 1}, "chexed": {"1": 0, "2": 0, "3": 0, "4": 0, "5": 0, "6": 1, "7": 0, "8": 0, "9": 0, "10": 0}, "cqyimo42": {"1": 0, "2": 0, "3": 0, "4": 0, "5": 0, "6": 0, "7": 0, "8": 0, "9": 1, "10": 0}, "dopenderbabyballer": {"1": 0, "2": 0, "3": 0, "4": 1, "5": 0, "6": 1, "7": 1, "8": 0, "9": 0, "10": 0}, "dopaminefive": {"1": 0, "2": 0, "3": 0, "4": 1, "5": 1, "6": 0, "7": 0, "8": 0, "9": 0, "10": 1}, "613sadnesses": {"1": 0, "2": 0, "3": 0, "4": 0, "5": 0, "6": 0, "7": 0, "8": 0, "9": 0, "10": 1}, "bakanaruto": {"1": 0, "2": 0, "3": 1, "4": 0, "5": 0, "6": 0, "7": 0, "8": 0, "9": 0, "10": 0}, "framed_phoenix": {"1": 0, "2": 0, "3": 0, "4": 0, "5": 0, "6": 0, "7": 0, "8": 0, "9": 2, "10": 0}, "cobashk": {"1": 0, "2": 0, "3": 0, "4": 1, "5": 0, "6": 0, "7": 0, "8": 0, "9": 0, "10": 1}, "monesles": {"1": 0, "2": 0, "3": 0, "4": 0, "5": 1, "6": 0, "7": 2, "8": 1, "9": 2, "10": 0}, "eikonoquit": {"1": 0, "2": 0, "3": 0, "4": 1, "5": 0, "6": 1, "7": 1, "8": 1, "9": 0, "10": 2}, "canadagreat": {"1": 0, "2": 0, "3": 0, "4": 0, "5": 0, "6": 1, "7": 0, "8": 0, "9": 0, "10": 0}, "thelight954": {"1": 0, "2": 0, "3": 0, "4": 0, "5": 0, "6": 0, "7": 0, "8": 0, "9": 0, "10": 1}, "cptbbq": {"1": 0, "2": 0, "3": 0, "4": 0, "5": 1, "6": 0, "7": 0, "8": 0, "9": 0, "10": 3}, "ventrixx": {"1": 0, "2": 1, "3": 0, "4": 0, "5": 0, "6": 0, "7": 0, "8": 0, "9": 0, "10": 0}, "ghosthenryzhou": {"1": 0, "2": 0, "3": 0, "4": 0, "5": 1, "6": 0, "7": 0, "8": 1, "9": 0, "10": 1}, "largev": {"1": 0, "2": 0, "3": 0, "4": 0, "5": 0, "6": 0, "7": 0, "8": 1, "9": 1, "10": 0}, "spicytuna1": {"1": 0, "2": 0, "3": 0, "4": 0, "5": 0, "6": 1, "7": 0, "8": 0, "9": 0, "10": 0}, "geometricv": {"1": 0, "2": 0, "3": 1, "4": 0, "5": 0, "6": 1, "7": 0, "8": 4, "9": 4, "10": 0}, "downsider": {"1": 0, "2": 0, "3": 0, "4": 0, "5": 0, "6": 0, "7": 0, "8": 0, "9": 1, "10": 0}, "jakob2000": {"1": 0, "2": 0, "3": 0, "4": 0, "5": 1, "6": 1, "7": 2, "8": 0, "9": 4, "10": 3}, "90wpmomg": {"1": 0, "2": 0, "3": 0, "4": 0, "5": 1, "6": 1, "7": 0, "8": 1, "9": 2, "10": 2}, "drunkvinni": {"1": 0, "2": 0, "3": 0, "4": 0, "5": 0, "6": 1, "7": 0, "8": 0, "9": 0, "10": 0}, "keegmosquito": {"1": 0, "2": 0, "3": 0, "4": 0, "5": 0, "6": 0, "7": 0, "8": 0, "9": 0, "10": 1}, "typingartist": {"1": 0, "2": 0, "3": 0, "4": 0, "5": 0, "6": 0, "7": 0, "8": 0, "9": 1, "10": 0}, "zzzak": {"1": 0, "2": 0, "3": 0, "4": 0, "5": 0, "6": 0, "7": 0, "8": 0, "9": 0, "10": 1}, "ggeznub": {"1": 0, "2": 0, "3": 0, "4": 0, "5": 0, "6": 0, "7": 0, "8": 0, "9": 0, "10": 1}, "pennywater": {"1": 0, "2": 0, "3": 0, "4": 0, "5": 1, "6": 2, "7": 1, "8": 1, "9": 1, "10": 0}, "allyosaugh": {"1": 0, "2": 0, "3": 0, "4": 1, "5": 0, "6": 0, "7": 0, "8": 0, "9": 0, "10": 0}, "dragoomba": {"1": 0, "2": 0, "3": 0, "4": 0, "5": 0, "6": 0, "7": 0, "8": 1, "9": 0, "10": 0}, "xbowsdotcom": {"1": 0, "2": 0, "3": 0, "4": 0, "5": 0, "6": 0, "7": 0, "8": 0, "9": 0, "10": 1}, "flyingkeys1": {"1": 0, "2": 0, "3": 0, "4": 0, "5": 0, "6": 1, "7": 1, "8": 3, "9": 2, "10": 0}, "notjimmy972": {"1": 0, "2": 0, "3": 0, "4": 0, "5": 0, "6": 1, "7": 2, "8": 0, "9": 0, "10": 1}, "alonelychime": {"1": 0, "2": 0, "3": 0, "4": 0, "5": 0, "6": 0, "7": 0, "8": 0, "9": 0, "10": 1}, "jackson24me": {"1": 0, "2": 0, "3": 0, "4": 0, "5": 1, "6": 0, "7": 0, "8": 0, "9": 0, "10": 0}, "breakneck3": {"1": 0, "2": 0, "3": 0, "4": 0, "5": 0, "6": 0, "7": 0, "8": 1, "9": 0, "10": 0}, "andreannq": {"1": 0, "2": 0, "3": 0, "4": 0, "5": 0, "6": 0, "7": 1, "8": 1, "9": 0, "10": 0}, "_vormx_": {"1": 0, "2": 0, "3": 0, "4": 0, "5": 0, "6": 0, "7": 0, "8": 0, "9": 1, "10": 1}, "bobbybobbo": {"1": 0, "2": 0, "3": 0, "4": 0, "5": 0, "6": 1, "7": 0, "8": 1, "9": 0, "10": 0}, "piimpjttv": {"1": 0, "2": 0, "3": 1, "4": 1, "5": 0, "6": 3, "7": 4, "8": 5, "9": 4, "10": 1}, "elmuchocapitano": {"1": 0, "2": 0, "3": 0, "4": 0, "5": 0, "6": 0, "7": 1, "8": 1, "9": 0, "10": 2}, "laptoptrash": {"1": 0, "2": 0, "3": 0, "4": 1, "5": 0, "6": 0, "7": 0, "8": 0, "9": 0, "10": 0}, "mikecmtong": {"1": 0, "2": 0, "3": 0, "4": 0, "5": 0, "6": 0, "7": 0, "8": 0, "9": 0, "10": 1}, "exalted": {"1": 0, "2": 0, "3": 0, "4": 0, "5": 2, "6": 1, "7": 0, "8": 0, "9": 0, "10": 0}, "fajitas_ye": {"1": 0, "2": 0, "3": 0, "4": 1, "5": 0, "6": 0, "7": 0, "8": 0, "9": 0, "10": 0}, "forestnymph": {"1": 0, "2": 0, "3": 0, "4": 0, "5": 0, "6": 0, "7": 0, "8": 0, "9": 0, "10": 1}, "kogasapls": {"1": 0, "2": 0, "3": 0, "4": 0, "5": 0, "6": 0, "7": 1, "8": 1, "9": 0, "10": 0}, "namess": {"1": 0, "2": 0, "3": 0, "4": 2, "5": 0, "6": 0, "7": 0, "8": 2, "9": 1, "10": 0}, "santaax": {"1": 0, "2": 1, "3": 0, "4": 0, "5": 0, "6": 0, "7": 0, "8": 0, "9": 0, "10": 0}, "violet_evergarden": {"1": 0, "2": 0, "3": 0, "4": 0, "5": 0, "6": 0, "7": 0, "8": 1, "9": 0, "10": 1}, "adnapahpla": {"1": 0, "2": 0, "3": 0, "4": 0, "5": 0, "6": 0, "7": 0, "8": 1, "9": 0, "10": 0}, "dopaminethree": {"1": 0, "2": 0, "3": 0, "4": 0, "5": 0, "6": 0, "7": 0, "8": 1, "9": 1, "10": 0}, "typinthatfast": {"1": 0, "2": 0, "3": 0, "4": 0, "5": 1, "6": 0, "7": 0, "8": 0, "9": 0, "10": 0}, "_jos_": {"1": 0, "2": 0, "3": 0, "4": 0, "5": 0, "6": 0, "7": 0, "8": 1, "9": 1, "10": 0}, "mattinato21": {"1": 0, "2": 0, "3": 0, "4": 0, "5": 1, "6": 0, "7": 0, "8": 0, "9": 0, "10": 0}, "keatonasmith": {"1": 0, "2": 0, "3": 0, "4": 0, "5": 0, "6": 2, "7": 0, "8": 0, "9": 2, "10": 1}, "lastofspades": {"1": 0, "2": 0, "3": 0, "4": 0, "5": 1, "6": 0, "7": 0, "8": 1, "9": 0, "10": 0}, "arxbombus": {"1": 0, "2": 1, "3": 0, "4": 0, "5": 0, "6": 0, "7": 1, "8": 0, "9": 0, "10": 0}, "wefwefa": {"1": 0, "2": 0, "3": 0, "4": 0, "5": 0, "6": 0, "7": 1, "8": 0, "9": 0, "10": 0}, "ghall": {"1": 0, "2": 0, "3": 0, "4": 0, "5": 0, "6": 0, "7": 0, "8": 0, "9": 0, "10": 1}, "viper45": {"1": 0, "2": 0, "3": 0, "4": 0, "5": 0, "6": 1, "7": 0, "8": 0, "9": 1, "10": 0}, "novoamor123": {"1": 0, "2": 0, "3": 0, "4": 0, "5": 0, "6": 0, "7": 0, "8": 1, "9": 0, "10": 0}, "_cool_super_nice_otter_": {"1": 0, "2": 0, "3": 0, "4": 1, "5": 0, "6": 0, "7": 0, "8": 0, "9": 0, "10": 0}, "dreadisfool": {"1": 0, "2": 0, "3": 0, "4": 0, "5": 0, "6": 0, "7": 0, "8": 0, "9": 1, "10": 0}, "zmaveegamd0m": {"1": 0, "2": 0, "3": 0, "4": 0, "5": 0, "6": 0, "7": 0, "8": 0, "9": 1, "10": 0}, "rapidlys": {"1": 0, "2": 0, "3": 0, "4": 0, "5": 1, "6": 0, "7": 0, "8": 0, "9": 0, "10": 0}, "limit405": {"1": 0, "2": 0, "3": 0, "4": 0, "5": 0, "6": 0, "7": 0, "8": 0, "9": 0, "10": 1}, "lalabird4": {"1": 0, "2": 0, "3": 0, "4": 0, "5": 0, "6": 1, "7": 0, "8": 0, "9": 0, "10": 1}, "zenokuthric": {"1": 0, "2": 0, "3": 0, "4": 0, "5": 0, "6": 1, "7": 0, "8": 1, "9": 0, "10": 0}, "kw2000": {"1": 0, "2": 0, "3": 0, "4": 0, "5": 0, "6": 0, "7": 1, "8": 0, "9": 0, "10": 0}, "lalabird6": {"1": 0, "2": 0, "3": 0, "4": 1, "5": 0, "6": 1, "7": 0, "8": 0, "9": 0, "10": 0}, "pndspirit": {"1": 0, "2": 0, "3": 0, "4": 0, "5": 0, "6": 0, "7": 1, "8": 0, "9": 0, "10": 0}, "distear": {"1": 0, "2": 0, "3": 0, "4": 0, "5": 1, "6": 0, "7": 0, "8": 0, "9": 0, "10": 0}, "playscrabble": {"1": 0, "2": 0, "3": 0, "4": 4, "5": 1, "6": 3, "7": 2, "8": 6, "9": 7, "10": 10}, "tkrajcar": {"1": 0, "2": 0, "3": 0, "4": 0, "5": 1, "6": 0, "7": 0, "8": 1, "9": 0, "10": 0}, "glaba": {"1": 0, "2": 0, "3": 0, "4": 0, "5": 1, "6": 0, "7": 0, "8": 0, "9": 0, "10": 0}, "tyronemega": {"1": 0, "2": 0, "3": 0, "4": 0, "5": 0, "6": 1, "7": 0, "8": 0, "9": 0, "10": 0}, "waterbird": {"1": 0, "2": 0, "3": 0, "4": 0, "5": 0, "6": 0, "7": 0, "8": 0, "9": 1, "10": 1}, "justinxu": {"1": 0, "2": 0, "3": 0, "4": 1, "5": 0, "6": 1, "7": 0, "8": 4, "9": 0, "10": 3}, "zyonicz": {"1": 1, "2": 0, "3": 0, "4": 0, "5": 0, "6": 1, "7": 0, "8": 0, "9": 0, "10": 0}, "fastfingerdude": {"1": 0, "2": 0, "3": 0, "4": 0, "5": 0, "6": 1, "7": 0, "8": 0, "9": 0, "10": 0}, "khamisfo2": {"1": 0, "2": 0, "3": 0, "4": 0, "5": 1, "6": 0, "7": 0, "8": 0, "9": 0, "10": 0}, "oryzamercury": {"1": 0, "2": 0, "3": 0, "4": 0, "5": 0, "6": 0, "7": 0, "8": 0, "9": 1, "10": 0}, "riverwalk": {"1": 0, "2": 0, "3": 0, "4": 0, "5": 0, "6": 1, "7": 1, "8": 1, "9": 0, "10": 1}, "accurateangelo": {"1": 0, "2": 0, "3": 0, "4": 0, "5": 0, "6": 1, "7": 0, "8": 0, "9": 0, "10": 0}, "randumbtyper": {"1": 0, "2": 0, "3": 0, "4": 0, "5": 0, "6": 0, "7": 3, "8": 3, "9": 1, "10": 0}, "ximkevin": {"1": 0, "2": 0, "3": 0, "4": 1, "5": 0, "6": 0, "7": 0, "8": 0, "9": 0, "10": 0}, "lysergico": {"1": 0, "2": 0, "3": 0, "4": 0, "5": 0, "6": 2, "7": 1, "8": 4, "9": 1, "10": 4}, "grootbeer": {"1": 0, "2": 0, "3": 0, "4": 1, "5": 0, "6": 0, "7": 0, "8": 0, "9": 0, "10": 0}, "hwody": {"1": 0, "2": 0, "3": 0, "4": 0, "5": 1, "6": 1, "7": 0, "8": 0, "9": 0, "10": 0}, "brandinothefilipino": {"1": 0, "2": 0, "3": 0, "4": 0, "5": 0, "6": 0, "7": 0, "8": 0, "9": 1, "10": 2}, "ownerizer": {"1": 0, "2": 0, "3": 0, "4": 0, "5": 0, "6": 0, "7": 0, "8": 0, "9": 0, "10": 1}, "dhunyc": {"1": 0, "2": 0, "3": 0, "4": 0, "5": 1, "6": 0, "7": 0, "8": 0, "9": 0, "10": 0}, "spondulix": {"1": 0, "2": 0, "3": 0, "4": 0, "5": 0, "6": 0, "7": 0, "8": 0, "9": 2, "10": 1}, "usmanmajeed12": {"1": 0, "2": 0, "3": 0, "4": 0, "5": 0, "6": 0, "7": 0, "8": 0, "9": 0, "10": 2}, "ajityahoo876": {"1": 0, "2": 1, "3": 0, "4": 0, "5": 0, "6": 0, "7": 0, "8": 0, "9": 0, "10": 0}, "bladevampirek": {"1": 1, "2": 0, "3": 0, "4": 0, "5": 2, "6": 2, "7": 2, "8": 9, "9": 13, "10": 14}, "eggshell24": {"1": 0, "2": 0, "3": 0, "4": 0, "5": 0, "6": 0, "7": 0, "8": 1, "9": 0, "10": 0}, "chaknqt": {"1": 0, "2": 0, "3": 0, "4": 0, "5": 1, "6": 0, "7": 0, "8": 0, "9": 0, "10": 0}, "zaj573": {"1": 0, "2": 0, "3": 0, "4": 0, "5": 0, "6": 0, "7": 1, "8": 0, "9": 0, "10": 0}, "indoviet": {"1": 0, "2": 0, "3": 0, "4": 0, "5": 0, "6": 0, "7": 0, "8": 0, "9": 0, "10": 1}, "wordracer888": {"1": 0, "2": 0, "3": 0, "4": 0, "5": 0, "6": 4, "7": 2, "8": 6, "9": 5, "10": 1}, "lithox2": {"1": 0, "2": 0, "3": 1, "4": 0, "5": 0, "6": 4, "7": 2, "8": 5, "9": 4, "10": 4}, "destroyerofkeys": {"1": 0, "2": 0, "3": 0, "4": 0, "5": 0, "6": 0, "7": 0, "8": 0, "9": 1, "10": 0}, "ebic_gamer": {"1": 0, "2": 0, "3": 0, "4": 0, "5": 0, "6": 0, "7": 0, "8": 0, "9": 1, "10": 1}, "mercyhurst": {"1": 0, "2": 0, "3": 0, "4": 0, "5": 0, "6": 0, "7": 0, "8": 0, "9": 1, "10": 0}, "duanjie": {"1": 0, "2": 0, "3": 0, "4": 0, "5": 0, "6": 0, "7": 0, "8": 1, "9": 0, "10": 3}, "tommypapa5": {"1": 0, "2": 0, "3": 0, "4": 0, "5": 0, "6": 0, "7": 0, "8": 1, "9": 0, "10": 0}, "lalalalallfalsdfas": {"1": 0, "2": 0, "3": 0, "4": 0, "5": 0, "6": 0, "7": 1, "8": 0, "9": 0, "10": 0}, "valvallecillo": {"1": 0, "2": 0, "3": 0, "4": 1, "5": 0, "6": 0, "7": 0, "8": 0, "9": 0, "10": 0}, "caffywin": {"1": 0, "2": 0, "3": 0, "4": 0, "5": 0, "6": 0, "7": 0, "8": 0, "9": 1, "10": 1}, "rrubinski": {"1": 0, "2": 0, "3": 0, "4": 0, "5": 0, "6": 0, "7": 0, "8": 0, "9": 0, "10": 1}, "joyjustin123": {"1": 0, "2": 0, "3": 0, "4": 0, "5": 0, "6": 0, "7": 1, "8": 0, "9": 0, "10": 0}, "meloodix00": {"1": 0, "2": 0, "3": 1, "4": 0, "5": 1, "6": 1, "7": 1, "8": 0, "9": 1, "10": 1}, "nitronix_": {"1": 0, "2": 0, "3": 0, "4": 0, "5": 0, "6": 0, "7": 1, "8": 0, "9": 0, "10": 0}, "sir_welch": {"1": 0, "2": 0, "3": 0, "4": 1, "5": 0, "6": 1, "7": 0, "8": 0, "9": 1, "10": 2}, "yayrin": {"1": 0, "2": 0, "3": 0, "4": 0, "5": 0, "6": 1, "7": 0, "8": 0, "9": 0, "10": 0}, "ultrashibe": {"1": 0, "2": 0, "3": 0, "4": 0, "5": 0, "6": 0, "7": 0, "8": 0, "9": 0, "10": 1}, "mdl_cmd": {"1": 0, "2": 0, "3": 1, "4": 0, "5": 0, "6": 0, "7": 0, "8": 0, "9": 0, "10": 0}, "dopamine6ix": {"1": 0, "2": 0, "3": 0, "4": 0, "5": 1, "6": 0, "7": 0, "8": 0, "9": 0, "10": 2}, "hangry": {"1": 0, "2": 0, "3": 0, "4": 0, "5": 0, "6": 0, "7": 0, "8": 0, "9": 0, "10": 1}, "poke1": {"1": 0, "2": 0, "3": 0, "4": 0, "5": 0, "6": 0, "7": 0, "8": 1, "9": 1, "10": 0}, "mastermark3": {"1": 0, "2": 0, "3": 0, "4": 0, "5": 0, "6": 0, "7": 1, "8": 0, "9": 0, "10": 0}, "l4ze": {"1": 0, "2": 0, "3": 1, "4": 0, "5": 1, "6": 0, "7": 0, "8": 0, "9": 1, "10": 1}, "ibexus": {"1": 0, "2": 0, "3": 1, "4": 0, "5": 0, "6": 1, "7": 0, "8": 0, "9": 0, "10": 2}, "poem": {"1": 0, "2": 0, "3": 0, "4": 1, "5": 1, "6": 0, "7": 3, "8": 2, "9": 4, "10": 11}, "arolakiv": {"1": 0, "2": 0, "3": 0, "4": 0, "5": 0, "6": 0, "7": 0, "8": 0, "9": 0, "10": 1}, "excetra": {"1": 0, "2": 0, "3": 0, "4": 0, "5": 0, "6": 0, "7": 0, "8": 2, "9": 3, "10": 2}, "nonquit13": {"1": 0, "2": 0, "3": 0, "4": 0, "5": 0, "6": 0, "7": 1, "8": 0, "9": 0, "10": 0}, "himajintyper": {"1": 0, "2": 0, "3": 0, "4": 0, "5": 0, "6": 0, "7": 2, "8": 2, "9": 5, "10": 5}, "timjeffery44": {"1": 0, "2": 0, "3": 0, "4": 1, "5": 1, "6": 7, "7": 4, "8": 15, "9": 10, "10": 18}, "rbbb": {"1": 0, "2": 0, "3": 0, "4": 0, "5": 0, "6": 0, "7": 0, "8": 0, "9": 0, "10": 1}, "avirella": {"1": 0, "2": 0, "3": 0, "4": 0, "5": 0, "6": 0, "7": 1, "8": 0, "9": 0, "10": 0}, "parse": {"1": 0, "2": 0, "3": 0, "4": 0, "5": 0, "6": 0, "7": 1, "8": 0, "9": 0, "10": 0}, "jimysucks": {"1": 0, "2": 0, "3": 0, "4": 0, "5": 0, "6": 0, "7": 0, "8": 0, "9": 0, "10": 1}, "penguinparadise": {"1": 0, "2": 0, "3": 0, "4": 1, "5": 0, "6": 0, "7": 0, "8": 0, "9": 0, "10": 0}, "johnnydarnsworth": {"1": 0, "2": 0, "3": 0, "4": 0, "5": 0, "6": 1, "7": 0, "8": 0, "9": 0, "10": 0}, "afzofa": {"1": 0, "2": 0, "3": 0, "4": 0, "5": 0, "6": 2, "7": 1, "8": 0, "9": 0, "10": 1}, "kappow": {"1": 0, "2": 0, "3": 0, "4": 0, "5": 0, "6": 0, "7": 0, "8": 0, "9": 0, "10": 1}, "javascriptz": {"1": 0, "2": 0, "3": 0, "4": 0, "5": 0, "6": 0, "7": 0, "8": 0, "9": 0, "10": 1}, "dev_rec": {"1": 0, "2": 1, "3": 0, "4": 0, "5": 0, "6": 0, "7": 0, "8": 0, "9": 0, "10": 0}, "qwestfinder": {"1": 0, "2": 0, "3": 0, "4": 0, "5": 0, "6": 0, "7": 0, "8": 1, "9": 0, "10": 0}, "baba55": {"1": 0, "2": 0, "3": 0, "4": 1, "5": 0, "6": 0, "7": 0, "8": 0, "9": 0, "10": 0}, "okami98": {"1": 0, "2": 0, "3": 0, "4": 0, "5": 0, "6": 0, "7": 0, "8": 0, "9": 1, "10": 0}, "asparagus_7454": {"1": 0, "2": 0, "3": 0, "4": 0, "5": 0, "6": 0, "7": 1, "8": 0, "9": 0, "10": 2}, "blvc": {"1": 0, "2": 0, "3": 0, "4": 1, "5": 0, "6": 0, "7": 0, "8": 0, "9": 0, "10": 0}, "cassdragon1": {"1": 0, "2": 0, "3": 0, "4": 0, "5": 0, "6": 0, "7": 1, "8": 0, "9": 0, "10": 0}, "mongomania": {"1": 0, "2": 0, "3": 0, "4": 0, "5": 0, "6": 0, "7": 0, "8": 1, "9": 1, "10": 0}, "euij": {"1": 0, "2": 0, "3": 0, "4": 0, "5": 0, "6": 0, "7": 1, "8": 1, "9": 1, "10": 0}, "daniel3131": {"1": 0, "2": 0, "3": 0, "4": 0, "5": 1, "6": 1, "7": 0, "8": 0, "9": 0, "10": 0}, "amadeus007": {"1": 0, "2": 0, "3": 0, "4": 0, "5": 0, "6": 1, "7": 0, "8": 0, "9": 0, "10": 0}, "graddiences": {"1": 0, "2": 0, "3": 0, "4": 0, "5": 0, "6": 0, "7": 0, "8": 0, "9": 1, "10": 0}, "acutesubduralhematoma": {"1": 0, "2": 0, "3": 0, "4": 0, "5": 0, "6": 0, "7": 0, "8": 1, "9": 0, "10": 0}, "notapplicable": {"1": 0, "2": 0, "3": 0, "4": 0, "5": 0, "6": 0, "7": 0, "8": 0, "9": 0, "10": 1}, "cypher_xd": {"1": 0, "2": 0, "3": 0, "4": 0, "5": 0, "6": 0, "7": 0, "8": 0, "9": 1, "10": 0}, "himynameisrohitsingh": {"1": 0, "2": 0, "3": 0, "4": 0, "5": 0, "6": 0, "7": 0, "8": 1, "9": 2, "10": 1}, "goldjet30_wow": {"1": 0, "2": 0, "3": 0, "4": 0, "5": 1, "6": 0, "7": 0, "8": 0, "9": 0, "10": 0}, "adnaan": {"1": 0, "2": 0, "3": 0, "4": 0, "5": 0, "6": 0, "7": 1, "8": 0, "9": 0, "10": 0}, "610momo": {"1": 0, "2": 0, "3": 0, "4": 0, "5": 0, "6": 0, "7": 0, "8": 0, "9": 0, "10": 1}, "staticnine": {"1": 0, "2": 0, "3": 0, "4": 0, "5": 0, "6": 2, "7": 0, "8": 0, "9": 0, "10": 1}, "mememachine420": {"1": 0, "2": 0, "3": 0, "4": 0, "5": 0, "6": 0, "7": 0, "8": 0, "9": 0, "10": 1}, "mas281": {"1": 0, "2": 0, "3": 0, "4": 0, "5": 0, "6": 0, "7": 0, "8": 1, "9": 0, "10": 0}, "robertoberst": {"1": 0, "2": 0, "3": 0, "4": 0, "5": 0, "6": 0, "7": 1, "8": 0, "9": 0, "10": 0}, "robloxplayer71499": {"1": 0, "2": 0, "3": 0, "4": 1, "5": 0, "6": 1, "7": 0, "8": 2, "9": 2, "10": 2}, "perlascope": {"1": 0, "2": 0, "3": 0, "4": 0, "5": 0, "6": 0, "7": 2, "8": 0, "9": 0, "10": 1}, "amandakk": {"1": 0, "2": 0, "3": 0, "4": 0, "5": 0, "6": 0, "7": 0, "8": 0, "9": 0, "10": 1}, "saberwing": {"1": 0, "2": 0, "3": 0, "4": 0, "5": 0, "6": 0, "7": 0, "8": 0, "9": 0, "10": 1}, "currentjoys": {"1": 0, "2": 0, "3": 1, "4": 0, "5": 2, "6": 0, "7": 1, "8": 0, "9": 2, "10": 0}, "learningthumbspace": {"1": 0, "2": 0, "3": 0, "4": 0, "5": 1, "6": 0, "7": 0, "8": 0, "9": 0, "10": 0}, "jacquesjacques": {"1": 0, "2": 0, "3": 0, "4": 0, "5": 0, "6": 0, "7": 0, "8": 1, "9": 0, "10": 0}, "kitkatforward": {"1": 0, "2": 0, "3": 0, "4": 0, "5": 0, "6": 0, "7": 0, "8": 0, "9": 1, "10": 0}, "duolingo": {"1": 0, "2": 0, "3": 1, "4": 0, "5": 0, "6": 0, "7": 0, "8": 0, "9": 0, "10": 0}, "douglasjones": {"1": 0, "2": 0, "3": 0, "4": 0, "5": 0, "6": 0, "7": 0, "8": 0, "9": 1, "10": 0}, "spiritualadventurer1729": {"1": 0, "2": 0, "3": 0, "4": 0, "5": 0, "6": 0, "7": 0, "8": 0, "9": 0, "10": 1}, "akfeeny": {"1": 0, "2": 0, "3": 0, "4": 0, "5": 0, "6": 0, "7": 0, "8": 1, "9": 0, "10": 0}, "dopaminefour": {"1": 0, "2": 0, "3": 0, "4": 0, "5": 0, "6": 0, "7": 1, "8": 0, "9": 0, "10": 0}, "suhmikeok": {"1": 0, "2": 0, "3": 0, "4": 0, "5": 0, "6": 0, "7": 0, "8": 0, "9": 1, "10": 0}, "canownueasy": {"1": 0, "2": 0, "3": 0, "4": 0, "5": 0, "6": 0, "7": 0, "8": 0, "9": 0, "10": 2}, "nishisushi": {"1": 0, "2": 0, "3": 0, "4": 0, "5": 0, "6": 0, "7": 0, "8": 0, "9": 1, "10": 0}, "macadmission": {"1": 0, "2": 0, "3": 0, "4": 0, "5": 0, "6": 0, "7": 0, "8": 1, "9": 0, "10": 0}, "123movies": {"1": 0, "2": 0, "3": 0, "4": 1, "5": 0, "6": 0, "7": 0, "8": 0, "9": 0, "10": 0}, "kspeed11": {"1": 0, "2": 0, "3": 0, "4": 0, "5": 0, "6": 0, "7": 0, "8": 0, "9": 0, "10": 1}, "n9ne": {"1": 0, "2": 0, "3": 0, "4": 0, "5": 1, "6": 0, "7": 0, "8": 0, "9": 0, "10": 0}, "therealsonic": {"1": 0, "2": 0, "3": 0, "4": 0, "5": 0, "6": 0, "7": 0, "8": 1, "9": 0, "10": 2}, "ssunatpure": {"1": 0, "2": 0, "3": 0, "4": 0, "5": 0, "6": 0, "7": 1, "8": 0, "9": 0, "10": 0}, "la_espada_y_la_rosa": {"1": 0, "2": 0, "3": 0, "4": 0, "5": 0, "6": 0, "7": 1, "8": 0, "9": 0, "10": 0}, "kula_": {"1": 0, "2": 0, "3": 0, "4": 0, "5": 0, "6": 0, "7": 0, "8": 0, "9": 0, "10": 1}, "boy_314": {"1": 0, "2": 0, "3": 0, "4": 0, "5": 0, "6": 0, "7": 2, "8": 0, "9": 1, "10": 0}, "kyol": {"1": 0, "2": 0, "3": 0, "4": 0, "5": 0, "6": 0, "7": 0, "8": 0, "9": 1, "10": 0}, "tryingchiclet": {"1": 0, "2": 0, "3": 1, "4": 0, "5": 0, "6": 0, "7": 0, "8": 0, "9": 0, "10": 0}, "sharkyboy": {"1": 0, "2": 0, "3": 0, "4": 0, "5": 0, "6": 0, "7": 0, "8": 0, "9": 0, "10": 1}, "killriam": {"1": 0, "2": 0, "3": 0, "4": 1, "5": 0, "6": 0, "7": 0, "8": 0, "9": 0, "10": 0}, "ferb007": {"1": 0, "2": 0, "3": 0, "4": 0, "5": 0, "6": 0, "7": 0, "8": 0, "9": 1, "10": 0}, "william_morris": {"1": 0, "2": 0, "3": 0, "4": 0, "5": 0, "6": 0, "7": 0, "8": 0, "9": 0, "10": 1}, "awigglemin": {"1": 0, "2": 0, "3": 0, "4": 0, "5": 0, "6": 0, "7": 0, "8": 0, "9": 1, "10": 0}, "mtgap": {"1": 0, "2": 0, "3": 0, "4": 0, "5": 0, "6": 0, "7": 0, "8": 0, "9": 1, "10": 1}, "rsuresh": {"1": 0, "2": 0, "3": 0, "4": 0, "5": 0, "6": 0, "7": 0, "8": 1, "9": 0, "10": 0}, "stev_cubed": {"1": 0, "2": 0, "3": 0, "4": 0, "5": 1, "6": 0, "7": 1, "8": 2, "9": 0, "10": 0}, "a87321dc00": {"1": 0, "2": 0, "3": 0, "4": 0, "5": 0, "6": 0, "7": 1, "8": 0, "9": 1, "10": 0}, "chesuccede": {"1": 0, "2": 0, "3": 0, "4": 0, "5": 0, "6": 0, "7": 1, "8": 0, "9": 0, "10": 0}, "jessiwho": {"1": 0, "2": 0, "3": 0, "4": 0, "5": 0, "6": 1, "7": 0, "8": 0, "9": 0, "10": 0}, "aquablitz11": {"1": 0, "2": 0, "3": 0, "4": 0, "5": 0, "6": 0, "7": 0, "8": 0, "9": 1, "10": 0}, "kjb3plover": {"1": 0, "2": 0, "3": 0, "4": 0, "5": 0, "6": 1, "7": 0, "8": 0, "9": 0, "10": 0}, "ryclic": {"1": 0, "2": 0, "3": 0, "4": 0, "5": 0, "6": 0, "7": 0, "8": 0, "9": 0, "10": 1}, "cwilkinson": {"1": 0, "2": 0, "3": 1, "4": 0, "5": 0, "6": 0, "7": 0, "8": 0, "9": 0, "10": 0}, "quadroopl": {"1": 0, "2": 0, "3": 0, "4": 0, "5": 0, "6": 0, "7": 0, "8": 0, "9": 0, "10": 1}, "pastelpink": {"1": 0, "2": 0, "3": 0, "4": 0, "5": 0, "6": 0, "7": 2, "8": 0, "9": 2, "10": 0}, "y0ink": {"1": 0, "2": 0, "3": 0, "4": 0, "5": 0, "6": 0, "7": 1, "8": 0, "9": 0, "10": 0}, "speedytypingyt": {"1": 0, "2": 0, "3": 0, "4": 1, "5": 1, "6": 0, "7": 0, "8": 2, "9": 0, "10": 0}, "andytixn": {"1": 0, "2": 0, "3": 0, "4": 0, "5": 1, "6": 0, "7": 0, "8": 0, "9": 0, "10": 0}, "clueou": {"1": 0, "2": 0, "3": 0, "4": 0, "5": 0, "6": 0, "7": 0, "8": 1, "9": 0, "10": 0}, "mathandphysicsftw": {"1": 0, "2": 0, "3": 0, "4": 0, "5": 1, "6": 2, "7": 3, "8": 0, "9": 4, "10": 3}, "flareor": {"1": 0, "2": 0, "3": 0, "4": 0, "5": 1, "6": 0, "7": 0, "8": 0, "9": 0, "10": 0}, "stephenleou15": {"1": 0, "2": 0, "3": 0, "4": 0, "5": 0, "6": 0, "7": 0, "8": 0, "9": 1, "10": 1}, "dogfoodlid": {"1": 0, "2": 0, "3": 1, "4": 0, "5": 0, "6": 0, "7": 0, "8": 0, "9": 1, "10": 4}, "flapjacks": {"1": 0, "2": 0, "3": 0, "4": 0, "5": 0, "6": 0, "7": 0, "8": 0, "9": 0, "10": 1}, "minijuice94": {"1": 0, "2": 0, "3": 0, "4": 0, "5": 0, "6": 0, "7": 0, "8": 0, "9": 1, "10": 0}, "mark40511": {"1": 0, "2": 0, "3": 0, "4": 0, "5": 0, "6": 6, "7": 14, "8": 21, "9": 40, "10": 28}, "ribombee": {"1": 0, "2": 0, "3": 0, "4": 1, "5": 0, "6": 0, "7": 0, "8": 0, "9": 0, "10": 1}, "ovecko": {"1": 0, "2": 0, "3": 0, "4": 0, "5": 0, "6": 0, "7": 0, "8": 0, "9": 1, "10": 0}, "abhib22": {"1": 0, "2": 0, "3": 0, "4": 0, "5": 0, "6": 0, "7": 0, "8": 1, "9": 0, "10": 0}, "hackermanheehee": {"1": 0, "2": 0, "3": 0, "4": 0, "5": 0, "6": 0, "7": 1, "8": 1, "9": 2, "10": 0}, "damaredayo": {"1": 0, "2": 0, "3": 0, "4": 0, "5": 0, "6": 0, "7": 0, "8": 0, "9": 1, "10": 0}, "customality": {"1": 0, "2": 0, "3": 0, "4": 0, "5": 0, "6": 0, "7": 0, "8": 0, "9": 0, "10": 1}, "jiedua": {"1": 0, "2": 0, "3": 0, "4": 0, "5": 0, "6": 2, "7": 0, "8": 0, "9": 0, "10": 0}, "tanami": {"1": 0, "2": 0, "3": 0, "4": 0, "5": 0, "6": 0, "7": 0, "8": 0, "9": 0, "10": 1}, "fivestarman": {"1": 0, "2": 0, "3": 0, "4": 0, "5": 0, "6": 0, "7": 0, "8": 0, "9": 2, "10": 0}, "hula_pie": {"1": 0, "2": 0, "3": 0, "4": 0, "5": 0, "6": 0, "7": 0, "8": 0, "9": 0, "10": 1}, "sophiiee": {"1": 0, "2": 0, "3": 0, "4": 0, "5": 0, "6": 0, "7": 0, "8": 0, "9": 0, "10": 1}, "xsession": {"1": 0, "2": 0, "3": 0, "4": 0, "5": 0, "6": 0, "7": 0, "8": 1, "9": 0, "10": 0}, "razertypist": {"1": 0, "2": 0, "3": 0, "4": 0, "5": 0, "6": 1, "7": 2, "8": 1, "9": 2, "10": 0}, "badbadkai": {"1": 0, "2": 0, "3": 0, "4": 0, "5": 0, "6": 0, "7": 0, "8": 0, "9": 0, "10": 1}, "misaka77": {"1": 0, "2": 0, "3": 0, "4": 0, "5": 0, "6": 0, "7": 0, "8": 0, "9": 0, "10": 1}, "hugeawesomeguy": {"1": 0, "2": 0, "3": 0, "4": 0, "5": 0, "6": 0, "7": 0, "8": 0, "9": 0, "10": 1}, "downplay": {"1": 0, "2": 0, "3": 0, "4": 0, "5": 0, "6": 0, "7": 0, "8": 0, "9": 2, "10": 0}, "kaaydawgg": {"1": 0, "2": 0, "3": 0, "4": 0, "5": 0, "6": 0, "7": 0, "8": 0, "9": 1, "10": 0}, "frontbink": {"1": 0, "2": 0, "3": 0, "4": 0, "5": 0, "6": 0, "7": 0, "8": 0, "9": 0, "10": 1}, "pjcrowley": {"1": 0, "2": 0, "3": 0, "4": 0, "5": 0, "6": 0, "7": 0, "8": 2, "9": 0, "10": 2}, "khronic": {"1": 0, "2": 0, "3": 0, "4": 0, "5": 0, "6": 5, "7": 8, "8": 23, "9": 16, "10": 31}, "clara22": {"1": 0, "2": 0, "3": 0, "4": 0, "5": 0, "6": 0, "7": 0, "8": 1, "9": 0, "10": 0}, "xyzrr": {"1": 0, "2": 0, "3": 0, "4": 0, "5": 0, "6": 0, "7": 0, "8": 0, "9": 1, "10": 1}, "struffoli": {"1": 0, "2": 0, "3": 0, "4": 0, "5": 0, "6": 0, "7": 0, "8": 0, "9": 1, "10": 0}, "dinowrecks": {"1": 0, "2": 0, "3": 0, "4": 0, "5": 0, "6": 0, "7": 1, "8": 0, "9": 0, "10": 0}, "dylan_9802": {"1": 0, "2": 0, "3": 0, "4": 0, "5": 0, "6": 1, "7": 1, "8": 2, "9": 4, "10": 2}, "oaksmudge": {"1": 0, "2": 0, "3": 0, "4": 0, "5": 0, "6": 1, "7": 0, "8": 0, "9": 0, "10": 0}, "solarscopez": {"1": 0, "2": 0, "3": 0, "4": 0, "5": 0, "6": 0, "7": 0, "8": 1, "9": 0, "10": 0}, "vfctyrant": {"1": 0, "2": 0, "3": 0, "4": 0, "5": 1, "6": 0, "7": 0, "8": 4, "9": 0, "10": 3}, "twwu": {"1": 0, "2": 0, "3": 0, "4": 0, "5": 0, "6": 0, "7": 0, "8": 1, "9": 0, "10": 0}, "sazuyano": {"1": 0, "2": 0, "3": 0, "4": 0, "5": 0, "6": 0, "7": 0, "8": 0, "9": 0, "10": 1}, "keeeeeeeelo": {"1": 0, "2": 0, "3": 0, "4": 0, "5": 0, "6": 0, "7": 0, "8": 0, "9": 0, "10": 1}, "sonic25549": {"1": 0, "2": 0, "3": 0, "4": 0, "5": 0, "6": 0, "7": 0, "8": 0, "9": 0, "10": 1}, "joshue27": {"1": 0, "2": 0, "3": 0, "4": 0, "5": 0, "6": 0, "7": 0, "8": 0, "9": 1, "10": 0}, "lesirh": {"1": 0, "2": 0, "3": 0, "4": 1, "5": 2, "6": 1, "7": 0, "8": 0, "9": 3, "10": 2}, "sayake": {"1": 0, "2": 0, "3": 0, "4": 0, "5": 0, "6": 0, "7": 1, "8": 0, "9": 0, "10": 0}, "val___": {"1": 0, "2": 0, "3": 0, "4": 0, "5": 0, "6": 0, "7": 0, "8": 0, "9": 0, "10": 1}, "oneshottoinfinity": {"1": 0, "2": 0, "3": 0, "4": 0, "5": 0, "6": 0, "7": 0, "8": 0, "9": 1, "10": 0}, "godfingerz": {"1": 0, "2": 0, "3": 0, "4": 0, "5": 0, "6": 0, "7": 0, "8": 0, "9": 0, "10": 1}, "hysteriaa": {"1": 0, "2": 0, "3": 0, "4": 0, "5": 0, "6": 0, "7": 0, "8": 3, "9": 0, "10": 3}, "jechew": {"1": 0, "2": 0, "3": 0, "4": 0, "5": 0, "6": 1, "7": 0, "8": 0, "9": 0, "10": 0}, "mokmoon": {"1": 0, "2": 0, "3": 0, "4": 0, "5": 0, "6": 0, "7": 0, "8": 0, "9": 0, "10": 1}, "nhima": {"1": 0, "2": 0, "3": 0, "4": 0, "5": 0, "6": 0, "7": 0, "8": 0, "9": 1, "10": 0}, "bigyoshi1": {"1": 0, "2": 0, "3": 0, "4": 0, "5": 0, "6": 0, "7": 0, "8": 1, "9": 0, "10": 0}, "g_fruit": {"1": 0, "2": 0, "3": 0, "4": 0, "5": 0, "6": 2, "7": 2, "8": 2, "9": 1, "10": 1}, "adamstrawberry": {"1": 0, "2": 0, "3": 0, "4": 0, "5": 0, "6": 1, "7": 0, "8": 0, "9": 0, "10": 0}, "baileyasset": {"1": 0, "2": 0, "3": 0, "4": 0, "5": 0, "6": 0, "7": 0, "8": 0, "9": 0, "10": 1}, "lubi222": {"1": 0, "2": 0, "3": 0, "4": 0, "5": 0, "6": 0, "7": 0, "8": 0, "9": 1, "10": 0}, "buttered_croissant": {"1": 0, "2": 0, "3": 0, "4": 0, "5": 0, "6": 0, "7": 0, "8": 0, "9": 0, "10": 1}, "chocojax": {"1": 0, "2": 0, "3": 0, "4": 0, "5": 0, "6": 0, "7": 0, "8": 1, "9": 0, "10": 0}, "asthesunshines": {"1": 0, "2": 0, "3": 0, "4": 0, "5": 0, "6": 1, "7": 0, "8": 0, "9": 0, "10": 0}, "jolocaust": {"1": 0, "2": 0, "3": 0, "4": 0, "5": 0, "6": 0, "7": 1, "8": 0, "9": 0, "10": 0}, "carpalxqgmlwy": {"1": 0, "2": 0, "3": 0, "4": 0, "5": 0, "6": 0, "7": 1, "8": 1, "9": 0, "10": 0}, "aram90": {"1": 0, "2": 0, "3": 0, "4": 0, "5": 0, "6": 0, "7": 0, "8": 0, "9": 1, "10": 0}, "spoonfedder999": {"1": 0, "2": 0, "3": 0, "4": 0, "5": 0, "6": 0, "7": 0, "8": 1, "9": 0, "10": 0}, "gorile": {"1": 0, "2": 0, "3": 0, "4": 0, "5": 0, "6": 0, "7": 0, "8": 1, "9": 0, "10": 0}, "roseftw": {"1": 0, "2": 0, "3": 0, "4": 0, "5": 0, "6": 0, "7": 0, "8": 0, "9": 0, "10": 1}, "hiddencupcake": {"1": 0, "2": 0, "3": 0, "4": 0, "5": 0, "6": 0, "7": 0, "8": 1, "9": 0, "10": 0}, "telken_is_co0l": {"1": 0, "2": 0, "3": 0, "4": 0, "5": 0, "6": 1, "7": 0, "8": 0, "9": 0, "10": 0}, "ginoo75": {"1": 0, "2": 0, "3": 0, "4": 0, "5": 0, "6": 0, "7": 3, "8": 3, "9": 3, "10": 11}, "kevy1": {"1": 0, "2": 0, "3": 0, "4": 0, "5": 0, "6": 0, "7": 0, "8": 1, "9": 0, "10": 0}, "neotyphe": {"1": 0, "2": 0, "3": 0, "4": 0, "5": 0, "6": 0, "7": 0, "8": 1, "9": 0, "10": 0}, "bbatliner": {"1": 0, "2": 0, "3": 0, "4": 0, "5": 0, "6": 0, "7": 0, "8": 0, "9": 1, "10": 0}, "sierra05": {"1": 0, "2": 0, "3": 0, "4": 0, "5": 1, "6": 0, "7": 0, "8": 1, "9": 1, "10": 0}, "dannesul1337": {"1": 0, "2": 0, "3": 0, "4": 0, "5": 0, "6": 0, "7": 0, "8": 0, "9": 0, "10": 1}, "g1_petroleum": {"1": 0, "2": 0, "3": 0, "4": 0, "5": 0, "6": 0, "7": 1, "8": 1, "9": 0, "10": 1}, "thispotatoguy": {"1": 0, "2": 0, "3": 0, "4": 0, "5": 0, "6": 0, "7": 0, "8": 1, "9": 0, "10": 0}, "leonzalion": {"1": 0, "2": 0, "3": 0, "4": 0, "5": 0, "6": 0, "7": 0, "8": 0, "9": 1, "10": 2}, "xswordiex": {"1": 0, "2": 0, "3": 0, "4": 0, "5": 0, "6": 0, "7": 0, "8": 0, "9": 1, "10": 0}, "paceyq": {"1": 0, "2": 0, "3": 0, "4": 0, "5": 0, "6": 0, "7": 0, "8": 0, "9": 2, "10": 1}, "lucryu": {"1": 0, "2": 0, "3": 0, "4": 0, "5": 0, "6": 0, "7": 0, "8": 0, "9": 1, "10": 0}, "alansupra": {"1": 0, "2": 0, "3": 0, "4": 0, "5": 0, "6": 0, "7": 0, "8": 0, "9": 1, "10": 0}, "krewe11a": {"1": 0, "2": 0, "3": 0, "4": 0, "5": 0, "6": 0, "7": 0, "8": 0, "9": 0, "10": 1}, "kayochin": {"1": 0, "2": 0, "3": 0, "4": 0, "5": 0, "6": 0, "7": 1, "8": 0, "9": 0, "10": 0}, "pastashapes": {"1": 0, "2": 0, "3": 0, "4": 0, "5": 0, "6": 0, "7": 2, "8": 2, "9": 5, "10": 2}, "deckonebell": {"1": 0, "2": 0, "3": 0, "4": 0, "5": 0, "6": 0, "7": 0, "8": 1, "9": 0, "10": 0}, "jlpt": {"1": 0, "2": 0, "3": 0, "4": 0, "5": 0, "6": 0, "7": 0, "8": 0, "9": 0, "10": 1}, "itskyle1995": {"1": 0, "2": 0, "3": 0, "4": 0, "5": 0, "6": 0, "7": 1, "8": 0, "9": 0, "10": 0}, "ekrpatdvorak": {"1": 0, "2": 0, "3": 0, "4": 0, "5": 0, "6": 0, "7": 1, "8": 1, "9": 0, "10": 0}, "kahow": {"1": 0, "2": 0, "3": 0, "4": 0, "5": 0, "6": 0, "7": 1, "8": 0, "9": 2, "10": 2}, "telorbusu": {"1": 0, "2": 0, "3": 0, "4": 0, "5": 0, "6": 0, "7": 0, "8": 1, "9": 0, "10": 0}, "basedbiff": {"1": 0, "2": 0, "3": 0, "4": 0, "5": 0, "6": 0, "7": 0, "8": 0, "9": 0, "10": 1}, "jacakira": {"1": 0, "2": 0, "3": 0, "4": 0, "5": 0, "6": 0, "7": 0, "8": 0, "9": 1, "10": 1}, "2fast4yo": {"1": 0, "2": 0, "3": 0, "4": 0, "5": 0, "6": 0, "7": 0, "8": 1, "9": 0, "10": 0}, "ashret": {"1": 0, "2": 0, "3": 0, "4": 0, "5": 0, "6": 0, "7": 0, "8": 0, "9": 1, "10": 0}, "pbnl2": {"1": 0, "2": 0, "3": 0, "4": 0, "5": 0, "6": 0, "7": 0, "8": 0, "9": 0, "10": 1}, "the_tigerlions": {"1": 0, "2": 0, "3": 0, "4": 0, "5": 0, "6": 0, "7": 0, "8": 0, "9": 0, "10": 1}, "rubberdome": {"1": 0, "2": 0, "3": 0, "4": 0, "5": 0, "6": 0, "7": 0, "8": 0, "9": 0, "10": 2}, "call_me_napkin": {"1": 0, "2": 0, "3": 0, "4": 0, "5": 0, "6": 0, "7": 1, "8": 0, "9": 1, "10": 0}, "cnry": {"1": 0, "2": 0, "3": 0, "4": 0, "5": 0, "6": 0, "7": 0, "8": 0, "9": 1, "10": 0}, "chills4shiverin": {"1": 0, "2": 0, "3": 0, "4": 0, "5": 0, "6": 0, "7": 0, "8": 0, "9": 0, "10": 1}, "flip2theleft": {"1": 0, "2": 0, "3": 0, "4": 0, "5": 0, "6": 0, "7": 0, "8": 0, "9": 1, "10": 0}, "bmsothom": {"1": 0, "2": 0, "3": 0, "4": 1, "5": 0, "6": 0, "7": 0, "8": 0, "9": 0, "10": 0}, "carrot_": {"1": 0, "2": 0, "3": 0, "4": 0, "5": 0, "6": 0, "7": 0, "8": 0, "9": 0, "10": 1}, "soword": {"1": 0, "2": 0, "3": 0, "4": 0, "5": 0, "6": 0, "7": 1, "8": 0, "9": 1, "10": 0}, "youngpioneer": {"1": 0, "2": 0, "3": 0, "4": 0, "5": 0, "6": 0, "7": 0, "8": 0, "9": 0, "10": 1}, "kevinhunter": {"1": 0, "2": 0, "3": 0, "4": 0, "5": 0, "6": 0, "7": 0, "8": 1, "9": 0, "10": 0}, "tubbsters": {"1": 0, "2": 0, "3": 0, "4": 0, "5": 0, "6": 0, "7": 0, "8": 1, "9": 1, "10": 0}, "n1ght": {"1": 0, "2": 0, "3": 0, "4": 0, "5": 0, "6": 0, "7": 0, "8": 0, "9": 1, "10": 0}, "inoahlot4": {"1": 0, "2": 0, "3": 0, "4": 0, "5": 0, "6": 0, "7": 0, "8": 0, "9": 0, "10": 1}, "e6f4e37l": {"1": 0, "2": 0, "3": 0, "4": 0, "5": 0, "6": 1, "7": 1, "8": 1, "9": 1, "10": 1}, "carlibou": {"1": 0, "2": 0, "3": 0, "4": 0, "5": 0, "6": 1, "7": 0, "8": 0, "9": 0, "10": 0}, "squareslice": {"1": 0, "2": 0, "3": 0, "4": 0, "5": 0, "6": 0, "7": 0, "8": 0, "9": 1, "10": 0}, "akitaspeedtyper": {"1": 0, "2": 0, "3": 0, "4": 0, "5": 0, "6": 0, "7": 0, "8": 0, "9": 1, "10": 0}, "mrcalamiteh": {"1": 0, "2": 0, "3": 0, "4": 0, "5": 0, "6": 0, "7": 0, "8": 0, "9": 0, "10": 1}, "glandock1": {"1": 0, "2": 0, "3": 0, "4": 0, "5": 0, "6": 0, "7": 0, "8": 0, "9": 0, "10": 1}, "ultralite": {"1": 0, "2": 0, "3": 0, "4": 0, "5": 0, "6": 1, "7": 0, "8": 0, "9": 0, "10": 0}, "bobchamp": {"1": 0, "2": 0, "3": 0, "4": 0, "5": 0, "6": 0, "7": 1, "8": 0, "9": 0, "10": 0}, "lunicia": {"1": 0, "2": 0, "3": 0, "4": 0, "5": 0, "6": 1, "7": 0, "8": 0, "9": 0, "10": 0}, "harshbarger.a@gmail.com": {"1": 0, "2": 0, "3": 0, "4": 0, "5": 0, "6": 0, "7": 0, "8": 1, "9": 0, "10": 0}, "peaslepuff": {"1": 0, "2": 0, "3": 0, "4": 0, "5": 0, "6": 0, "7": 0, "8": 0, "9": 1, "10": 0}, "amirdann": {"1": 0, "2": 0, "3": 0, "4": 0, "5": 0, "6": 0, "7": 0, "8": 0, "9": 0, "10": 1}, "onahc": {"1": 0, "2": 0, "3": 0, "4": 2, "5": 0, "6": 0, "7": 0, "8": 0, "9": 1, "10": 0}, "just_sayori": {"1": 0, "2": 0, "3": 0, "4": 0, "5": 0, "6": 0, "7": 0, "8": 0, "9": 0, "10": 3}, "vanp": {"1": 0, "2": 0, "3": 0, "4": 0, "5": 0, "6": 0, "7": 0, "8": 1, "9": 0, "10": 0}, "hi_im_chobo": {"1": 0, "2": 0, "3": 0, "4": 0, "5": 0, "6": 0, "7": 0, "8": 0, "9": 0, "10": 1}, "rahul4562": {"1": 0, "2": 0, "3": 0, "4": 0, "5": 0, "6": 0, "7": 0, "8": 0, "9": 0, "10": 1}, "meenepo": {"1": 0, "2": 0, "3": 0, "4": 0, "5": 0, "6": 0, "7": 0, "8": 0, "9": 1, "10": 0}, "choober": {"1": 0, "2": 0, "3": 0, "4": 0, "5": 0, "6": 0, "7": 0, "8": 0, "9": 0, "10": 1}, "redtr5": {"1": 0, "2": 0, "3": 0, "4": 0, "5": 0, "6": 1, "7": 0, "8": 0, "9": 0, "10": 0}, "noodlicious": {"1": 0, "2": 0, "3": 0, "4": 0, "5": 0, "6": 0, "7": 1, "8": 0, "9": 0, "10": 0}, "ngjinghao": {"1": 0, "2": 0, "3": 0, "4": 0, "5": 0, "6": 0, "7": 1, "8": 0, "9": 0, "10": 0}, "jayneidhart": {"1": 0, "2": 0, "3": 0, "4": 0, "5": 0, "6": 0, "7": 0, "8": 0, "9": 0, "10": 1}, "mattycraps": {"1": 0, "2": 0, "3": 0, "4": 0, "5": 0, "6": 0, "7": 0, "8": 0, "9": 1, "10": 0}, "leydrich": {"1": 0, "2": 0, "3": 0, "4": 0, "5": 0, "6": 0, "7": 0, "8": 0, "9": 0, "10": 1}, "asdfdatav": {"1": 0, "2": 0, "3": 0, "4": 0, "5": 0, "6": 0, "7": 0, "8": 0, "9": 1, "10": 0}, "potatoritos": {"1": 0, "2": 0, "3": 0, "4": 0, "5": 0, "6": 0, "7": 0, "8": 0, "9": 0, "10": 1}, "drav22": {"1": 0, "2": 0, "3": 0, "4": 0, "5": 0, "6": 0, "7": 1, "8": 0, "9": 0, "10": 0}, "ponchotang": {"1": 0, "2": 0, "3": 0, "4": 0, "5": 0, "6": 0, "7": 1, "8": 0, "9": 0, "10": 0}, "purple_kisa": {"1": 0, "2": 0, "3": 0, "4": 0, "5": 0, "6": 0, "7": 0, "8": 1, "9": 0, "10": 0}, "kingaristeia": {"1": 0, "2": 0, "3": 0, "4": 0, "5": 0, "6": 0, "7": 0, "8": 0, "9": 1, "10": 0}, "jestercaporado": {"1": 0, "2": 0, "3": 1, "4": 0, "5": 0, "6": 0, "7": 0, "8": 0, "9": 4, "10": 0}, "super_not_pro": {"1": 0, "2": 0, "3": 0, "4": 0, "5": 0, "6": 0, "7": 0, "8": 0, "9": 0, "10": 1}, "rmsitar": {"1": 0, "2": 0, "3": 0, "4": 0, "5": 0, "6": 0, "7": 0, "8": 0, "9": 1, "10": 0}, "parkourwizard": {"1": 0, "2": 0, "3": 0, "4": 0, "5": 0, "6": 0, "7": 0, "8": 0, "9": 0, "10": 1}, "richivinsky": {"1": 0, "2": 0, "3": 0, "4": 0, "5": 0, "6": 0, "7": 1, "8": 0, "9": 0, "10": 0}, "mysticalfire1315": {"1": 0, "2": 0, "3": 0, "4": 0, "5": 0, "6": 0, "7": 1, "8": 0, "9": 0, "10": 0}, "fryth_42": {"1": 0, "2": 0, "3": 0, "4": 0, "5": 0, "6": 0, "7": 0, "8": 0, "9": 1, "10": 2}, "schattendolch": {"1": 0, "2": 0, "3": 0, "4": 0, "5": 0, "6": 0, "7": 0, "8": 0, "9": 1, "10": 0}, "clarified": {"1": 0, "2": 0, "3": 0, "4": 0, "5": 0, "6": 0, "7": 0, "8": 0, "9": 0, "10": 1}, "drlawc2": {"1": 0, "2": 0, "3": 0, "4": 0, "5": 0, "6": 0, "7": 0, "8": 0, "9": 1, "10": 0}, "happypappy21": {"1": 0, "2": 0, "3": 0, "4": 0, "5": 0, "6": 0, "7": 0, "8": 0, "9": 1, "10": 0}, "ironicninja": {"1": 0, "2": 0, "3": 0, "4": 0, "5": 0, "6": 0, "7": 0, "8": 0, "9": 1, "10": 0}, "queenjkim": {"1": 0, "2": 0, "3": 0, "4": 0, "5": 0, "6": 0, "7": 0, "8": 0, "9": 1, "10": 0}, "hulkamaniabrother": {"1": 0, "2": 0, "3": 0, "4": 0, "5": 0, "6": 0, "7": 0, "8": 0, "9": 0, "10": 1}, "godamongstslowtypers": {"1": 0, "2": 0, "3": 0, "4": 0, "5": 0, "6": 0, "7": 0, "8": 1, "9": 0, "10": 0}, "vck3000": {"1": 0, "2": 0, "3": 0, "4": 0, "5": 0, "6": 0, "7": 1, "8": 0, "9": 0, "10": 0}, "vitalsine1": {"1": 0, "2": 0, "3": 0, "4": 0, "5": 0, "6": 0, "7": 0, "8": 1, "9": 0, "10": 0}, "robert1997": {"1": 0, "2": 0, "3": 0, "4": 0, "5": 0, "6": 1, "7": 0, "8": 0, "9": 0, "10": 0}, "bigmeat11": {"1": 0, "2": 0, "3": 0, "4": 0, "5": 0, "6": 0, "7": 0, "8": 0, "9": 0, "10": 1}, "wjsprowler": {"1": 0, "2": 0, "3": 0, "4": 0, "5": 1, "6": 0, "7": 0, "8": 0, "9": 0, "10": 0}, "togahimiko": {"1": 0, "2": 0, "3": 0, "4": 0, "5": 0, "6": 0, "7": 0, "8": 0, "9": 0, "10": 1}, "samboofer69": {"1": 0, "2": 0, "3": 0, "4": 0, "5": 0, "6": 0, "7": 0, "8": 0, "9": 0, "10": 1}, "150nonquit": {"1": 0, "2": 0, "3": 0, "4": 0, "5": 0, "6": 1, "7": 0, "8": 0, "9": 0, "10": 0}, "cryotiks": {"1": 0, "2": 0, "3": 0, "4": 0, "5": 0, "6": 0, "7": 0, "8": 0, "9": 1, "10": 0}, "ecfigies": {"1": 0, "2": 0, "3": 0, "4": 0, "5": 0, "6": 0, "7": 0, "8": 0, "9": 1, "10": 0}, "thedragonemperor": {"1": 0, "2": 0, "3": 0, "4": 0, "5": 0, "6": 0, "7": 0, "8": 0, "9": 1, "10": 2}, "mixxanber": {"1": 0, "2": 0, "3": 0, "4": 0, "5": 0, "6": 1, "7": 0, "8": 0, "9": 0, "10": 0}, "haru1": {"1": 0, "2": 0, "3": 0, "4": 0, "5": 0, "6": 0, "7": 0, "8": 0, "9": 1, "10": 0}, "danfanlol": {"1": 0, "2": 0, "3": 0, "4": 0, "5": 0, "6": 0, "7": 1, "8": 0, "9": 0, "10": 0}, "bently5102": {"1": 0, "2": 0, "3": 0, "4": 0, "5": 0, "6": 0, "7": 0, "8": 0, "9": 0, "10": 1}, "haris2015": {"1": 0, "2": 0, "3": 0, "4": 0, "5": 0, "6": 0, "7": 0, "8": 0, "9": 2, "10": 0}, "minicho": {"1": 0, "2": 0, "3": 0, "4": 0, "5": 0, "6": 0, "7": 0, "8": 1, "9": 0, "10": 0}, "tinaqt": {"1": 0, "2": 0, "3": 0, "4": 0, "5": 0, "6": 0, "7": 0, "8": 0, "9": 1, "10": 0}, "ardous": {"1": 0, "2": 0, "3": 0, "4": 0, "5": 0, "6": 0, "7": 1, "8": 0, "9": 0, "10": 0}, "noprop": {"1": 0, "2": 0, "3": 0, "4": 0, "5": 0, "6": 0, "7": 0, "8": 0, "9": 0, "10": 1}, "overdosed": {"1": 0, "2": 0, "3": 0, "4": 0, "5": 0, "6": 0, "7": 1, "8": 0, "9": 0, "10": 0}, "emperorpenquin": {"1": 0, "2": 0, "3": 0, "4": 0, "5": 0, "6": 0, "7": 0, "8": 0, "9": 1, "10": 0}, "codeone": {"1": 0, "2": 0, "3": 0, "4": 0, "5": 0, "6": 0, "7": 0, "8": 0, "9": 0, "10": 1}, "stanleythezheng": {"1": 0, "2": 0, "3": 0, "4": 0, "5": 0, "6": 0, "7": 0, "8": 1, "9": 0, "10": 0}, "m1234d": {"1": 0, "2": 0, "3": 0, "4": 0, "5": 0, "6": 0, "7": 0, "8": 0, "9": 1, "10": 0}, "arijan": {"1": 0, "2": 0, "3": 0, "4": 0, "5": 0, "6": 0, "7": 1, "8": 0, "9": 0, "10": 0}, "andyyy68": {"1": 0, "2": 0, "3": 0, "4": 0, "5": 0, "6": 0, "7": 0, "8": 1, "9": 0, "10": 0}, "sazonhason": {"1": 0, "2": 0, "3": 0, "4": 0, "5": 0, "6": 0, "7": 0, "8": 0, "9": 1, "10": 0}, "supercool22": {"1": 0, "2": 0, "3": 0, "4": 0, "5": 0, "6": 0, "7": 0, "8": 0, "9": 0, "10": 1}, "enscarr": {"1": 0, "2": 0, "3": 0, "4": 0, "5": 0, "6": 0, "7": 0, "8": 0, "9": 0, "10": 1}, "zambrix": {"1": 0, "2": 0, "3": 0, "4": 0, "5": 0, "6": 0, "7": 1, "8": 0, "9": 0, "10": 0}, "insanegamerwow": {"1": 0, "2": 0, "3": 0, "4": 0, "5": 0, "6": 0, "7": 0, "8": 1, "9": 0, "10": 0}, "josasim": {"1": 0, "2": 0, "3": 0, "4": 0, "5": 0, "6": 0, "7": 0, "8": 0, "9": 0, "10": 1}, "ahchai": {"1": 0, "2": 0, "3": 0, "4": 0, "5": 0, "6": 0, "7": 0, "8": 0, "9": 0, "10": 1}, "deskripper": {"1": 0, "2": 0, "3": 0, "4": 0, "5": 0, "6": 0, "7": 0, "8": 1, "9": 1, "10": 2}, "chqnges": {"1": 0, "2": 0, "3": 0, "4": 0, "5": 0, "6": 0, "7": 0, "8": 0, "9": 1, "10": 0}, "transfusion": {"1": 0, "2": 0, "3": 0, "4": 0, "5": 0, "6": 0, "7": 0, "8": 0, "9": 0, "10": 1}, "viinyl": {"1": 0, "2": 0, "3": 0, "4": 1, "5": 0, "6": 0, "7": 1, "8": 0, "9": 0, "10": 0}, "patagucci_girl": {"1": 0, "2": 0, "3": 0, "4": 0, "5": 0, "6": 0, "7": 0, "8": 0, "9": 1, "10": 0}, "diyen": {"1": 0, "2": 0, "3": 0, "4": 0, "5": 0, "6": 0, "7": 0, "8": 1, "9": 0, "10": 0}, "amun": {"1": 0, "2": 0, "3": 0, "4": 0, "5": 0, "6": 1, "7": 0, "8": 0, "9": 1, "10": 0}, "676339784": {"1": 0, "2": 0, "3": 0, "4": 0, "5": 0, "6": 1, "7": 0, "8": 0, "9": 0, "10": 0}, "itskadenhere": {"1": 0, "2": 0, "3": 0, "4": 0, "5": 0, "6": 0, "7": 1, "8": 0, "9": 0, "10": 0}, "joshuawn": {"1": 0, "2": 0, "3": 0, "4": 0, "5": 0, "6": 0, "7": 0, "8": 0, "9": 0, "10": 1}, "gianthetaco": {"1": 0, "2": 0, "3": 0, "4": 0, "5": 0, "6": 0, "7": 0, "8": 0, "9": 0, "10": 1}, "lsdb9742": {"1": 0, "2": 0, "3": 0, "4": 0, "5": 0, "6": 0, "7": 0, "8": 0, "9": 0, "10": 1}, "jchan18": {"1": 0, "2": 0, "3": 0, "4": 0, "5": 0, "6": 0, "7": 0, "8": 1, "9": 0, "10": 0}, "boomminecraft8": {"1": 0, "2": 0, "3": 0, "4": 0, "5": 0, "6": 0, "7": 0, "8": 0, "9": 1, "10": 0}, "nielsjensen": {"1": 0, "2": 0, "3": 0, "4": 0, "5": 0, "6": 0, "7": 0, "8": 0, "9": 0, "10": 1}, "dunklioscious": {"1": 0, "2": 0, "3": 0, "4": 0, "5": 0, "6": 0, "7": 0, "8": 0, "9": 1, "10": 0}, "racerrob": {"1": 0, "2": 0, "3": 0, "4": 0, "5": 0, "6": 0, "7": 0, "8": 0, "9": 0, "10": 1}, "primetime979": {"1": 0, "2": 0, "3": 0, "4": 0, "5": 0, "6": 0, "7": 1, "8": 0, "9": 0, "10": 0}, "mollyqt": {"1": 0, "2": 0, "3": 0, "4": 0, "5": 0, "6": 0, "7": 0, "8": 1, "9": 0, "10": 0}, "hestah": {"1": 0, "2": 0, "3": 0, "4": 0, "5": 0, "6": 0, "7": 1, "8": 0, "9": 0, "10": 0}, "orangutan": {"1": 0, "2": 0, "3": 0, "4": 0, "5": 0, "6": 0, "7": 0, "8": 0, "9": 1, "10": 0}, "harnessingxd": {"1": 0, "2": 0, "3": 0, "4": 0, "5": 0, "6": 0, "7": 0, "8": 0, "9": 0, "10": 1}, "ragemodeon": {"1": 0, "2": 0, "3": 0, "4": 0, "5": 0, "6": 0, "7": 0, "8": 1, "9": 0, "10": 0}, "lazyperson99": {"1": 0, "2": 0, "3": 0, "4": 0, "5": 0, "6": 0, "7": 0, "8": 0, "9": 0, "10": 1}, "emilewarot": {"1": 0, "2": 0, "3": 0, "4": 0, "5": 0, "6": 0, "7": 0, "8": 0, "9": 0, "10": 1}, "chad_gamer": {"1": 0, "2": 0, "3": 0, "4": 0, "5": 0, "6": 0, "7": 0, "8": 0, "9": 0, "10": 1}, "5000600": {"1": 0, "2": 0, "3": 0, "4": 0, "5": 0, "6": 0, "7": 1, "8": 0, "9": 0, "10": 0}, "lorusx": {"1": 0, "2": 0, "3": 0, "4": 0, "5": 0, "6": 0, "7": 0, "8": 1, "9": 0, "10": 0}, "magsi": {"1": 0, "2": 0, "3": 0, "4": 0, "5": 0, "6": 0, "7": 0, "8": 0, "9": 0, "10": 1}, "marlonk": {"1": 0, "2": 0, "3": 0, "4": 0, "5": 0, "6": 0, "7": 0, "8": 0, "9": 1, "10": 0}, "jonnsby": {"1": 0, "2": 0, "3": 0, "4": 0, "5": 0, "6": 0, "7": 0, "8": 0, "9": 0, "10": 1}, "super33": {"1": 0, "2": 0, "3": 0, "4": 0, "5": 0, "6": 0, "7": 0, "8": 0, "9": 0, "10": 1}, "joelthesuperior": {"1": 0, "2": 0, "3": 0, "4": 0, "5": 0, "6": 0, "7": 1, "8": 0, "9": 0, "10": 0}, "potus_donaldtrump": {"1": 0, "2": 0, "3": 0, "4": 0, "5": 0, "6": 0, "7": 0, "8": 0, "9": 1, "10": 0}, "relambrien": {"1": 0, "2": 0, "3": 0, "4": 0, "5": 0, "6": 1, "7": 0, "8": 0, "9": 0, "10": 0}, "furysummoner": {"1": 0, "2": 0, "3": 0, "4": 0, "5": 0, "6": 0, "7": 0, "8": 0, "9": 0, "10": 1}, "grayeyes": {"1": 0, "2": 0, "3": 0, "4": 0, "5": 0, "6": 0, "7": 0, "8": 2, "9": 0, "10": 0}, "bagnana": {"1": 0, "2": 0, "3": 0, "4": 0, "5": 0, "6": 0, "7": 0, "8": 1, "9": 0, "10": 0}, "triklino": {"1": 0, "2": 0, "3": 0, "4": 0, "5": 0, "6": 0, "7": 0, "8": 0, "9": 0, "10": 1}, "kaleetan": {"1": 0, "2": 0, "3": 0, "4": 0, "5": 0, "6": 0, "7": 1, "8": 0, "9": 0, "10": 0}, "ivan28283": {"1": 0, "2": 0, "3": 0, "4": 0, "5": 0, "6": 0, "7": 0, "8": 0, "9": 0, "10": 1}, "festivized": {"1": 1, "2": 0, "3": 0, "4": 0, "5": 0, "6": 0, "7": 0, "8": 0, "9": 0, "10": 0}, "disciple_yt": {"1": 0, "2": 1, "3": 0, "4": 0, "5": 0, "6": 0, "7": 0, "8": 0, "9": 0, "10": 0}, "roengrey1": {"1": 0, "2": 0, "3": 1, "4": 0, "5": 0, "6": 0, "7": 0, "8": 0, "9": 0, "10": 0}, "bruhmoment911": {"1": 0, "2": 0, "3": 0, "4": 1, "5": 0, "6": 0, "7": 0, "8": 0, "9": 0, "10": 0}, "konpiv": {"1": 0, "2": 0, "3": 0, "4": 0, "5": 1, "6": 0, "7": 0, "8": 0, "9": 0, "10": 0}, "m3r8": {"1": 0, "2": 0, "3": 0, "4": 0, "5": 0, "6": 1, "7": 0, "8": 0, "9": 0, "10": 0}, "sebastiancv": {"1": 0, "2": 0, "3": 0, "4": 0, "5": 0, "6": 0, "7": 1, "8": 0, "9": 0, "10": 0}, "juicedit": {"1": 0, "2": 0, "3": 0, "4": 0, "5": 0, "6": 0, "7": 0, "8": 1, "9": 0, "10": 0}, "cortmarshal": {"1": 0, "2": 0, "3": 0, "4": 0, "5": 0, "6": 0, "7": 0, "8": 0, "9": 1, "10": 0}, "clam8218": {"1": 0, "2": 0, "3": 0, "4": 0, "5": 0, "6": 0, "7": 0, "8": 0, "9": 0, "10": 1}, "xrtforces": {"1": 0, "2": 0, "3": 0, "4": 0, "5": 0, "6": 0, "7": 0, "8": 0, "9": 1, "10": 0}, "t2fast4u": {"1": 0, "2": 0, "3": 0, "4": 0, "5": 0, "6": 0, "7": 0, "8": 0, "9": 0, "10": 1}, "fatelool": {"1": 0, "2": 0, "3": 0, "4": 0, "5": 0, "6": 0, "7": 1, "8": 0, "9": 0, "10": 0}, "geononquit": {"1": 0, "2": 0, "3": 0, "4": 0, "5": 0, "6": 0, "7": 0, "8": 0, "9": 0, "10": 1}, "imfastafbooiii": {"1": 0, "2": 0, "3": 0, "4": 0, "5": 0, "6": 0, "7": 0, "8": 0, "9": 0, "10": 1}, "questionablechoices": {"1": 0, "2": 0, "3": 0, "4": 0, "5": 0, "6": 0, "7": 0, "8": 1, "9": 0, "10": 0}, "sydneykimbell": {"1": 0, "2": 0, "3": 0, "4": 0, "5": 0, "6": 0, "7": 0, "8": 0, "9": 0, "10": 1}, "pingle": {"1": 0, "2": 0, "3": 0, "4": 0, "5": 0, "6": 0, "7": 0, "8": 0, "9": 1, "10": 0}, "tesseractbeyond": {"1": 0, "2": 0, "3": 0, "4": 0, "5": 0, "6": 0, "7": 0, "8": 0, "9": 1, "10": 0}, "no_good_": {"1": 0, "2": 0, "3": 0, "4": 0, "5": 0, "6": 0, "7": 0, "8": 1, "9": 0, "10": 0}, "last updated": 1605664969.282166}